{"generation": 10, "populations": [{"generation": 10, "goal": "0", "chromosomes": [{"uuid": "cc724b6e-25ab-4b7a-beec-00061ffa4dd2", "generation": 10, "genes": [{"identifier": "0", "value": "{0}"}, {"identifier": "1", "value": "{1, 2}"}, {"identifier": "2", "value": "{-1}"}, {"identifier": "3", "value": "{0}"}, {"identifier": "4", "value": "{1}"}, {"identifier": "5", "value": "{1, -1}"}, {"identifier": "6", "value": "{1, 2}"}, {"identifier": "7", "value": "{0, 1}"}, {"identifier": "8", "value": "{0}"}, {"identifier": "9", "value": "{1, -1}"}, {"identifier": "10", "value": "{2}"}, {"identifier": "11", "value": "{0, 1}"}, {"identifier": "12", "value": "{0}"}, {"identifier": "13", "value": "{0, 2}"}, {"identifier": "14", "value": "{0, 1}"}, {"identifier": "15", "value": "{0, -1}"}, {"identifier": "16", "value": "{2}"}, {"identifier": "17", "value": "{1, 2}"}, {"identifier": "18", "value": "{1, -1}"}, {"identifier": "19", "value": "{1, -1}"}, {"identifier": "20", "value": "{0}"}, {"identifier": "21", "value": "{0}"}, {"identifier": "22", "value": "{2}"}, {"identifier": "23", "value": "{0}"}, {"identifier": "24", "value": "{0, 1}"}], "fitness": "0.7469952030006315", "parents": ["f9b0954e-9425-4084-b5fc-60ef8d77c49c", "9a85eb6b-df00-4eb4-9e2b-f16e17f8cc94"]}, {"uuid": "61010d9d-4bbc-49b4-9783-b9d0dc1d4d94", "generation": 10, "genes": [{"identifier": "0", "value": "{0}"}, {"identifier": "1", "value": "{1, 2}"}, {"identifier": "2", "value": "{-1}"}, {"identifier": "3", "value": "{0}"}, {"identifier": "4", "value": "{0}"}, {"identifier": "5", "value": "{1, -1}"}, {"identifier": "6", "value": "{0, -1}"}, {"identifier": "7", "value": "{0, 1}"}, {"identifier": "8", "value": "{0}"}, {"identifier": "9", "value": "{1, -1}"}, {"identifier": "10", "value": "{2}"}, {"identifier": "11", "value": "{0, 1}"}, {"identifier": "12", "value": "{0}"}, {"identifier": "13", "value": "{0, 2}"}, {"identifier": "14", "value": "{-1}"}, {"identifier": "15", "value": "{0, -1}"}, {"identifier": "16", "value": "{2}"}, {"identifier": "17", "value": "{1, 2}"}, {"identifier": "18", "value": "{1, -1}"}, {"identifier": "19", "value": "{1, -1}"}, {"identifier": "20", "value": "{1}"}, {"identifier": "21", "value": "{1, 2}"}, {"identifier": "22", "value": "{2}"}, {"identifier": "23", "value": "{0}"}, {"identifier": "24", "value": "{0, 1}"}], "fitness": "0.6874584203299535", "parents": ["9a85eb6b-df00-4eb4-9e2b-f16e17f8cc94", "d7dbcb08-09f6-4cac-a941-5d4962087226"]}, {"uuid": "9b3fb58a-5c8f-4585-923e-48872c2044cc", "generation": 6, "genes": [{"identifier": "0", "value": "{0}"}, {"identifier": "1", "value": "{1, 2}"}, {"identifier": "2", "value": "{-1}"}, {"identifier": "3", "value": "{0}"}, {"identifier": "4", "value": "{1}"}, {"identifier": "5", "value": "{1, -1}"}, {"identifier": "6", "value": "{0, -1}"}, {"identifier": "7", "value": "{2}"}, {"identifier": "8", "value": "set()"}, {"identifier": "9", "value": "{1, -1}"}, {"identifier": "10", "value": "{2}"}, {"identifier": "11", "value": "{0, 1}"}, {"identifier": "12", "value": "{0}"}, {"identifier": "13", "value": "{0}"}, {"identifier": "14", "value": "{0, 1}"}, {"identifier": "15", "value": "{0, -1}"}, {"identifier": "16", "value": "{2}"}, {"identifier": "17", "value": "{1, 2}"}, {"identifier": "18", "value": "{1, -1}"}, {"identifier": "19", "value": "{1, -1}"}, {"identifier": "20", "value": "{0}"}, {"identifier": "21", "value": "{1, 2}"}, {"identifier": "22", "value": "{2}"}, {"identifier": "23", "value": "{0}"}, {"identifier": "24", "value": "{0, 1}"}], "fitness": "0.658422363899287", "parents": ["83dcae4c-78a6-4f54-8eb5-77c96a02514b", "34dae494-8864-4a36-9fe3-007c74a25ab0"]}, {"uuid": "89c7005b-7ed5-4c84-8e67-4bcce074d49d", "generation": 10, "genes": [{"identifier": "0", "value": "{0}"}, {"identifier": "1", "value": "{1, 2}"}, {"identifier": "2", "value": "{-1}"}, {"identifier": "3", "value": "{0}"}, {"identifier": "4", "value": "{0}"}, {"identifier": "5", "value": "{0}"}, {"identifier": "6", "value": "{0, -1}"}, {"identifier": "7", "value": "{0, 1}"}, {"identifier": "8", "value": "{-1}"}, {"identifier": "9", "value": "{1, -1}"}, {"identifier": "10", "value": "{2}"}, {"identifier": "11", "value": "{0, 1}"}, {"identifier": "12", "value": "{0}"}, {"identifier": "13", "value": "{0, 2}"}, {"identifier": "14", "value": "{0, 1}"}, {"identifier": "15", "value": "{0, -1}"}, {"identifier": "16", "value": "{2}"}, {"identifier": "17", "value": "{1, 2}"}, {"identifier": "18", "value": "{1, -1}"}, {"identifier": "19", "value": "{1, -1}"}, {"identifier": "20", "value": "{1}"}, {"identifier": "21", "value": "{0}"}, {"identifier": "22", "value": "{2}"}, {"identifier": "23", "value": "{0}"}, {"identifier": "24", "value": "{0, 1}"}], "fitness": "0.7118282897971848", "parents": ["d7dbcb08-09f6-4cac-a941-5d4962087226", "9a85eb6b-df00-4eb4-9e2b-f16e17f8cc94"]}, {"uuid": "5fbfaab4-9b5e-4c9b-b1b0-ed86bea204ef", "generation": 9, "genes": [{"identifier": "0", "value": "{0, 1}"}, {"identifier": "1", "value": "{1, 2}"}, {"identifier": "2", "value": "{-1}"}, {"identifier": "3", "value": "{-1}"}, {"identifier": "4", "value": "{-1}"}, {"identifier": "5", "value": "{2}"}, {"identifier": "6", "value": "{0, -1}"}, {"identifier": "7", "value": "{1}"}, {"identifier": "8", "value": "set()"}, {"identifier": "9", "value": "{1}"}, {"identifier": "10", "value": "{2}"}, {"identifier": "11", "value": "{0}"}, {"identifier": "12", "value": "{0}"}, {"identifier": "13", "value": "{0}"}, {"identifier": "14", "value": "{0, 1}"}, {"identifier": "15", "value": "{0, -1}"}, {"identifier": "16", "value": "{2}"}, {"identifier": "17", "value": "{1, 2}"}, {"identifier": "18", "value": "{1, -1}"}, {"identifier": "19", "value": "{1}"}, {"identifier": "20", "value": "{1}"}, {"identifier": "21", "value": "{0, 2}"}, {"identifier": "22", "value": "{2}"}, {"identifier": "23", "value": "{0}"}, {"identifier": "24", "value": "{0, 1}"}], "fitness": "0.6007855971603343", "parents": ["87fa9eb1-2c3a-49c8-84b1-6b75e765e5a9", "ed6b4499-1d39-4881-86fc-3e40269b1ec3"]}, {"uuid": "739e1872-074d-4eeb-ba7c-160c8290457e", "generation": 9, "genes": [{"identifier": "0", "value": "{-1}"}, {"identifier": "1", "value": "{1}"}, {"identifier": "2", "value": "{-1}"}, {"identifier": "3", "value": "{0}"}, {"identifier": "4", "value": "{1}"}, {"identifier": "5", "value": "{1, -1}"}, {"identifier": "6", "value": "{0, -1}"}, {"identifier": "7", "value": "{2}"}, {"identifier": "8", "value": "set()"}, {"identifier": "9", "value": "{1, -1}"}, {"identifier": "10", "value": "{2}"}, {"identifier": "11", "value": "{0, 1}"}, {"identifier": "12", "value": "{0}"}, {"identifier": "13", "value": "{0, 2}"}, {"identifier": "14", "value": "{-1}"}, {"identifier": "15", "value": "{0, -1}"}, {"identifier": "16", "value": "{2}"}, {"identifier": "17", "value": "{1, 2}"}, {"identifier": "18", "value": "{1, -1}"}, {"identifier": "19", "value": "{0, 1}"}, {"identifier": "20", "value": "{0}"}, {"identifier": "21", "value": "{0, 2}"}, {"identifier": "22", "value": "{2}"}, {"identifier": "23", "value": "{0}"}, {"identifier": "24", "value": "{0, 1}"}], "fitness": "0.5962787166599051", "parents": ["9b3fb58a-5c8f-4585-923e-48872c2044cc", "a0db439e-5f1b-4802-82b2-18a5925f4df9"]}, {"uuid": "ff23e343-a6d4-4f5d-b8cd-0656e10594d0", "generation": 10, "genes": [{"identifier": "0", "value": "{0}"}, {"identifier": "1", "value": "{1, 2}"}, {"identifier": "2", "value": "{-1}"}, {"identifier": "3", "value": "{0}"}, {"identifier": "4", "value": "{1}"}, {"identifier": "5", "value": "{1, -1}"}, {"identifier": "6", "value": "{0, -1}"}, {"identifier": "7", "value": "{0, 1}"}, {"identifier": "8", "value": "{-1}"}, {"identifier": "9", "value": "{1, -1}"}, {"identifier": "10", "value": "{2}"}, {"identifier": "11", "value": "{0, 1}"}, {"identifier": "12", "value": "{0}"}, {"identifier": "13", "value": "{0, 2}"}, {"identifier": "14", "value": "{-1}"}, {"identifier": "15", "value": "{-1}"}, {"identifier": "16", "value": "{2}"}, {"identifier": "17", "value": "{1, 2}"}, {"identifier": "18", "value": "{1, -1}"}, {"identifier": "19", "value": "{1, -1}"}, {"identifier": "20", "value": "{0}"}, {"identifier": "21", "value": "{1, 2}"}, {"identifier": "22", "value": "{-1}"}, {"identifier": "23", "value": "{0}"}, {"identifier": "24", "value": "{0, 1}"}], "fitness": "0.6317844141054032", "parents": ["f9b0954e-9425-4084-b5fc-60ef8d77c49c", "9a85eb6b-df00-4eb4-9e2b-f16e17f8cc94"]}, {"uuid": "a85964dc-bb6b-4342-bf2d-2adb98b63767", "generation": 10, "genes": [{"identifier": "0", "value": "{0}"}, {"identifier": "1", "value": "{1}"}, {"identifier": "2", "value": "{-1}"}, {"identifier": "3", "value": "{0}"}, {"identifier": "4", "value": "{1}"}, {"identifier": "5", "value": "{0}"}, {"identifier": "6", "value": "{1, 2}"}, {"identifier": "7", "value": "{0}"}, {"identifier": "8", "value": "{-1}"}, {"identifier": "9", "value": "{1, -1}"}, {"identifier": "10", "value": "{2}"}, {"identifier": "11", "value": "{0, 1}"}, {"identifier": "12", "value": "{0}"}, {"identifier": "13", "value": "{0, 2}"}, {"identifier": "14", "value": "{0, 1}"}, {"identifier": "15", "value": "{0, -1}"}, {"identifier": "16", "value": "{2}"}, {"identifier": "17", "value": "{1, 2}"}, {"identifier": "18", "value": "{1, -1}"}, {"identifier": "19", "value": "{1, -1}"}, {"identifier": "20", "value": "{0}"}, {"identifier": "21", "value": "{0}"}, {"identifier": "22", "value": "{-1}"}, {"identifier": "23", "value": "{0}"}, {"identifier": "24", "value": "{0, 1}"}], "fitness": "0.68310434805456", "parents": ["9a85eb6b-df00-4eb4-9e2b-f16e17f8cc94", "d7dbcb08-09f6-4cac-a941-5d4962087226"]}, {"uuid": "41bca159-142b-4860-bd07-0dd9844b13d9", "generation": 7, "genes": [{"identifier": "0", "value": "{-1}"}, {"identifier": "1", "value": "{1}"}, {"identifier": "2", "value": "{-1}"}, {"identifier": "3", "value": "{-1}"}, {"identifier": "4", "value": "{1}"}, {"identifier": "5", "value": "{1, -1}"}, {"identifier": "6", "value": "{0, -1}"}, {"identifier": "7", "value": "{0, 1}"}, {"identifier": "8", "value": "{-1}"}, {"identifier": "9", "value": "{0}"}, {"identifier": "10", "value": "{2}"}, {"identifier": "11", "value": "{2}"}, {"identifier": "12", "value": "{0}"}, {"identifier": "13", "value": "{1}"}, {"identifier": "14", "value": "{0, 1}"}, {"identifier": "15", "value": "{0, -1}"}, {"identifier": "16", "value": "{2}"}, {"identifier": "17", "value": "{0, -1}"}, {"identifier": "18", "value": "{1}"}, {"identifier": "19", "value": "{0, 1}"}, {"identifier": "20", "value": "{0}"}, {"identifier": "21", "value": "{0, 2}"}, {"identifier": "22", "value": "{-1}"}, {"identifier": "23", "value": "{0, 2}"}, {"identifier": "24", "value": "{-1}"}], "fitness": "0.5666036009061867", "parents": ["c48d3da2-0091-4fdc-bdd7-da6e32835324", "38366fb0-2a41-4a77-a087-be0ced35bfad"]}, {"uuid": "408329d2-2698-477a-80b8-b2ddaf3c7725", "generation": 10, "genes": [{"identifier": "0", "value": "{0}"}, {"identifier": "1", "value": "{1, 2}"}, {"identifier": "2", "value": "{-1}"}, {"identifier": "3", "value": "{0}"}, {"identifier": "4", "value": "{1}"}, {"identifier": "5", "value": "{1, -1}"}, {"identifier": "6", "value": "{0, -1}"}, {"identifier": "7", "value": "{0, 1}"}, {"identifier": "8", "value": "{0}"}, {"identifier": "9", "value": "{1, -1}"}, {"identifier": "10", "value": "{2}"}, {"identifier": "11", "value": "{0, 1}"}, {"identifier": "12", "value": "{0}"}, {"identifier": "13", "value": "{0, 2}"}, {"identifier": "14", "value": "{-1}"}, {"identifier": "15", "value": "{0, -1}"}, {"identifier": "16", "value": "{2}"}, {"identifier": "17", "value": "{1, 2}"}, {"identifier": "18", "value": "{1, -1}"}, {"identifier": "19", "value": "{1, -1}"}, {"identifier": "20", "value": "{1}"}, {"identifier": "21", "value": "{1, 2}"}, {"identifier": "22", "value": "{-1}"}, {"identifier": "23", "value": "{0}"}, {"identifier": "24", "value": "{0, 1}"}], "fitness": "0.6912690021282172", "parents": ["9a85eb6b-df00-4eb4-9e2b-f16e17f8cc94", "d7dbcb08-09f6-4cac-a941-5d4962087226"]}, {"uuid": "991a6d00-c6ed-4c30-b9da-55fb16a30743", "generation": 10, "genes": [{"identifier": "0", "value": "{0}"}, {"identifier": "1", "value": "{1, 2}"}, {"identifier": "2", "value": "{-1}"}, {"identifier": "3", "value": "{0}"}, {"identifier": "4", "value": "{1}"}, {"identifier": "5", "value": "{1, -1}"}, {"identifier": "6", "value": "{0, -1}"}, {"identifier": "7", "value": "{0, 1}"}, {"identifier": "8", "value": "{-1}"}, {"identifier": "9", "value": "{1, -1}"}, {"identifier": "10", "value": "{2}"}, {"identifier": "11", "value": "{0, 1}"}, {"identifier": "12", "value": "{0}"}, {"identifier": "13", "value": "{0, 2}"}, {"identifier": "14", "value": "{1}"}, {"identifier": "15", "value": "{0, -1}"}, {"identifier": "16", "value": "{2}"}, {"identifier": "17", "value": "{1, 2}"}, {"identifier": "18", "value": "{1, -1}"}, {"identifier": "19", "value": "{1, -1}"}, {"identifier": "20", "value": "{0}"}, {"identifier": "21", "value": "{1, 2}"}, {"identifier": "22", "value": "{-1}"}, {"identifier": "23", "value": "{0}"}, {"identifier": "24", "value": "{0, 1}"}], "fitness": "0.6907736881726921", "parents": ["f9b0954e-9425-4084-b5fc-60ef8d77c49c", "51b6ae00-a148-4817-9923-e88e1138f70c"]}], "best": 0.7469952030006315, "average": 0.6604821494740322, "median": 0.6317844141054032, "std": 0.052702051869612174}, {"generation": 10, "goal": "1", "chromosomes": [{"uuid": "c59729b5-9a0e-4cb0-b9d3-84b01bf6733f", "generation": 9, "genes": [{"identifier": "0", "value": "{1}"}, {"identifier": "1", "value": "{0, 1}"}, {"identifier": "2", "value": "{2}"}, {"identifier": "3", "value": "{0, 2}"}, {"identifier": "4", "value": "{-1}"}, {"identifier": "5", "value": "{1, -1}"}, {"identifier": "6", "value": "{1, 2}"}, {"identifier": "7", "value": "{0, -1}"}, {"identifier": "8", "value": "{1}"}, {"identifier": "9", "value": "{1, -1}"}, {"identifier": "10", "value": "{0, 2}"}, {"identifier": "11", "value": "{0, 2}"}, {"identifier": "12", "value": "{1}"}, {"identifier": "13", "value": "{1, -1}"}, {"identifier": "14", "value": "{1}"}, {"identifier": "15", "value": "{0, -1}"}, {"identifier": "16", "value": "{1, -1}"}, {"identifier": "17", "value": "{2, -1}"}, {"identifier": "18", "value": "{0}"}, {"identifier": "19", "value": "{0}"}, {"identifier": "20", "value": "{1, 2}"}, {"identifier": "21", "value": "{0, 1}"}, {"identifier": "22", "value": "{1, 2}"}, {"identifier": "23", "value": "{0, 1}"}, {"identifier": "24", "value": "{1}"}], "fitness": "0.7146903196124822", "parents": ["258ac832-1b20-47d4-a02e-7d3e6ff0ed8a", "de2a0785-c15e-408d-bb19-45d9e753b97a"]}, {"uuid": "c11615ae-912b-44a3-b01f-ccf054b83535", "generation": 9, "genes": [{"identifier": "0", "value": "{1}"}, {"identifier": "1", "value": "{0, 1}"}, {"identifier": "2", "value": "{2}"}, {"identifier": "3", "value": "{0, 2}"}, {"identifier": "4", "value": "{-1}"}, {"identifier": "5", "value": "{1, -1}"}, {"identifier": "6", "value": "{1, 2}"}, {"identifier": "7", "value": "{0, -1}"}, {"identifier": "8", "value": "{1}"}, {"identifier": "9", "value": "{1, -1}"}, {"identifier": "10", "value": "{0, 2}"}, {"identifier": "11", "value": "{0, 2}"}, {"identifier": "12", "value": "{1}"}, {"identifier": "13", "value": "{1, -1}"}, {"identifier": "14", "value": "{1}"}, {"identifier": "15", "value": "{0, -1}"}, {"identifier": "16", "value": "{2}"}, {"identifier": "17", "value": "{2, -1}"}, {"identifier": "18", "value": "{0, -1}"}, {"identifier": "19", "value": "{0}"}, {"identifier": "20", "value": "{1, 2}"}, {"identifier": "21", "value": "{0, 1}"}, {"identifier": "22", "value": "{1, 2}"}, {"identifier": "23", "value": "{0, 1}"}, {"identifier": "24", "value": "{1}"}], "fitness": "0.6831314919985116", "parents": ["1f9b9f2e-2e38-40d4-92c9-ef93f2b70708", "de2a0785-c15e-408d-bb19-45d9e753b97a"]}, {"uuid": "9392b5ab-8253-4035-9912-004ff70d5e76", "generation": 9, "genes": [{"identifier": "0", "value": "{1}"}, {"identifier": "1", "value": "{0, 1}"}, {"identifier": "2", "value": "{2}"}, {"identifier": "3", "value": "{0, 2}"}, {"identifier": "4", "value": "{-1}"}, {"identifier": "5", "value": "{1, -1}"}, {"identifier": "6", "value": "{1, 2}"}, {"identifier": "7", "value": "{0, -1}"}, {"identifier": "8", "value": "{1}"}, {"identifier": "9", "value": "{1, -1}"}, {"identifier": "10", "value": "{0, 2}"}, {"identifier": "11", "value": "{0, 2}"}, {"identifier": "12", "value": "{1}"}, {"identifier": "13", "value": "set()"}, {"identifier": "14", "value": "{2}"}, {"identifier": "15", "value": "{0, -1}"}, {"identifier": "16", "value": "{2}"}, {"identifier": "17", "value": "{2, -1}"}, {"identifier": "18", "value": "{0, -1}"}, {"identifier": "19", "value": "{0}"}, {"identifier": "20", "value": "{1, 2}"}, {"identifier": "21", "value": "{0, 1}"}, {"identifier": "22", "value": "{1, 2}"}, {"identifier": "23", "value": "{0, 1}"}, {"identifier": "24", "value": "{1}"}], "fitness": "0.619207082401321", "parents": ["1f9b9f2e-2e38-40d4-92c9-ef93f2b70708", "de2a0785-c15e-408d-bb19-45d9e753b97a"]}, {"uuid": "6d4be824-942f-4a48-8e9a-039f8b0de6a9", "generation": 7, "genes": [{"identifier": "0", "value": "{1}"}, {"identifier": "1", "value": "{-1}"}, {"identifier": "2", "value": "{2}"}, {"identifier": "3", "value": "{0}"}, {"identifier": "4", "value": "{-1}"}, {"identifier": "5", "value": "{1, -1}"}, {"identifier": "6", "value": "{1}"}, {"identifier": "7", "value": "{0, -1}"}, {"identifier": "8", "value": "{1}"}, {"identifier": "9", "value": "{1, -1}"}, {"identifier": "10", "value": "{0, 2}"}, {"identifier": "11", "value": "{0, 2}"}, {"identifier": "12", "value": "{1}"}, {"identifier": "13", "value": "{1, -1}"}, {"identifier": "14", "value": "{1}"}, {"identifier": "15", "value": "{1}"}, {"identifier": "16", "value": "{1, -1}"}, {"identifier": "17", "value": "{-1}"}, {"identifier": "18", "value": "{1}"}, {"identifier": "19", "value": "{0}"}, {"identifier": "20", "value": "{1, 2}"}, {"identifier": "21", "value": "{0, 1}"}, {"identifier": "22", "value": "{1}"}, {"identifier": "23", "value": "{0, 1}"}, {"identifier": "24", "value": "{1}"}], "fitness": "0.673977619022016", "parents": ["72e71ab3-dadb-4ec6-9fb7-a31801d35b1f", "35a01c46-e46d-4bbc-b477-508f7f99b0ab"]}, {"uuid": "03b9beec-2e25-4365-89aa-e449cfa36561", "generation": 10, "genes": [{"identifier": "0", "value": "{1}"}, {"identifier": "1", "value": "{0, 1}"}, {"identifier": "2", "value": "{2}"}, {"identifier": "3", "value": "{0, 2}"}, {"identifier": "4", "value": "{-1}"}, {"identifier": "5", "value": "{1, -1}"}, {"identifier": "6", "value": "{1, 2}"}, {"identifier": "7", "value": "{0, -1}"}, {"identifier": "8", "value": "{1}"}, {"identifier": "9", "value": "{1, -1}"}, {"identifier": "10", "value": "{0, 2}"}, {"identifier": "11", "value": "{0, 2}"}, {"identifier": "12", "value": "{1}"}, {"identifier": "13", "value": "{1, -1}"}, {"identifier": "14", "value": "{1}"}, {"identifier": "15", "value": "{0, -1}"}, {"identifier": "16", "value": "{1, -1}"}, {"identifier": "17", "value": "{2, -1}"}, {"identifier": "18", "value": "{0, -1}"}, {"identifier": "19", "value": "{0}"}, {"identifier": "20", "value": "{1, 2}"}, {"identifier": "21", "value": "{0, 1}"}, {"identifier": "22", "value": "{1, 2}"}, {"identifier": "23", "value": "{0, 1}"}, {"identifier": "24", "value": "{1}"}], "fitness": "0.7146903196124822", "parents": ["258ac832-1b20-47d4-a02e-7d3e6ff0ed8a", "c11615ae-912b-44a3-b01f-ccf054b83535"]}, {"uuid": "cde21644-9b99-4d5e-8ad0-1e84bdee091f", "generation": 10, "genes": [{"identifier": "0", "value": "{1}"}, {"identifier": "1", "value": "{-1}"}, {"identifier": "2", "value": "{2}"}, {"identifier": "3", "value": "{0}"}, {"identifier": "4", "value": "{-1}"}, {"identifier": "5", "value": "{1, -1}"}, {"identifier": "6", "value": "{1}"}, {"identifier": "7", "value": "{0, -1}"}, {"identifier": "8", "value": "{1}"}, {"identifier": "9", "value": "{1, -1}"}, {"identifier": "10", "value": "{0, 2}"}, {"identifier": "11", "value": "{0, 2}"}, {"identifier": "12", "value": "{1}"}, {"identifier": "13", "value": "{1, -1}"}, {"identifier": "14", "value": "{1}"}, {"identifier": "15", "value": "{1}"}, {"identifier": "16", "value": "{1, -1}"}, {"identifier": "17", "value": "{-1}"}, {"identifier": "18", "value": "{0, -1}"}, {"identifier": "19", "value": "{0}"}, {"identifier": "20", "value": "{1, 2}"}, {"identifier": "21", "value": "{0, 1}"}, {"identifier": "22", "value": "{1}"}, {"identifier": "23", "value": "{0, 1}"}, {"identifier": "24", "value": "{1}"}], "fitness": "0.6665744913171672", "parents": ["258ac832-1b20-47d4-a02e-7d3e6ff0ed8a", "6d4be824-942f-4a48-8e9a-039f8b0de6a9"]}, {"uuid": "88881acf-9cf6-45f6-95cf-0146a8b57b31", "generation": 6, "genes": [{"identifier": "0", "value": "{1}"}, {"identifier": "1", "value": "{0, 1}"}, {"identifier": "2", "value": "{2}"}, {"identifier": "3", "value": "{0, 2}"}, {"identifier": "4", "value": "{-1}"}, {"identifier": "5", "value": "{1, -1}"}, {"identifier": "6", "value": "{2}"}, {"identifier": "7", "value": "{0, -1}"}, {"identifier": "8", "value": "{1}"}, {"identifier": "9", "value": "{0}"}, {"identifier": "10", "value": "{0, 2}"}, {"identifier": "11", "value": "{0, 2}"}, {"identifier": "12", "value": "{1}"}, {"identifier": "13", "value": "{1, -1}"}, {"identifier": "14", "value": "{2}"}, {"identifier": "15", "value": "{1}"}, {"identifier": "16", "value": "{2}"}, {"identifier": "17", "value": "{2, -1}"}, {"identifier": "18", "value": "{0, -1}"}, {"identifier": "19", "value": "{0}"}, {"identifier": "20", "value": "{1, 2}"}, {"identifier": "21", "value": "{0, 1}"}, {"identifier": "22", "value": "{0, 2}"}, {"identifier": "23", "value": "{0, 1}"}, {"identifier": "24", "value": "{1}"}], "fitness": "0.6134499576853933", "parents": ["1674b6ed-f5f1-4041-9a16-6e4b1df6d90e", "6cd8d3f8-ce0e-4bed-8068-db66f4a87c32"]}, {"uuid": "94ce7c4a-2581-4f5e-9223-b6d4bcb1ca7c", "generation": 9, "genes": [{"identifier": "0", "value": "{1}"}, {"identifier": "1", "value": "{0, 1}"}, {"identifier": "2", "value": "{2}"}, {"identifier": "3", "value": "{0}"}, {"identifier": "4", "value": "{-1}"}, {"identifier": "5", "value": "{1, -1}"}, {"identifier": "6", "value": "{1, 2}"}, {"identifier": "7", "value": "{0, -1}"}, {"identifier": "8", "value": "{1}"}, {"identifier": "9", "value": "{1, -1}"}, {"identifier": "10", "value": "{0, 2}"}, {"identifier": "11", "value": "{0, 2}"}, {"identifier": "12", "value": "{1}"}, {"identifier": "13", "value": "{1, -1}"}, {"identifier": "14", "value": "{2}"}, {"identifier": "15", "value": "{0, -1}"}, {"identifier": "16", "value": "{2}"}, {"identifier": "17", "value": "{2, -1}"}, {"identifier": "18", "value": "{0, -1}"}, {"identifier": "19", "value": "{0}"}, {"identifier": "20", "value": "{1, 2}"}, {"identifier": "21", "value": "{0, 1}"}, {"identifier": "22", "value": "{1, 2}"}, {"identifier": "23", "value": "{0, 1}"}, {"identifier": "24", "value": "{1}"}], "fitness": "0.6515469837876526", "parents": ["258ac832-1b20-47d4-a02e-7d3e6ff0ed8a", "de2a0785-c15e-408d-bb19-45d9e753b97a"]}, {"uuid": "93373ca5-5cc3-4011-9fca-aa52e7ab339e", "generation": 10, "genes": [{"identifier": "0", "value": "{1}"}, {"identifier": "1", "value": "{0, 1}"}, {"identifier": "2", "value": "{2}"}, {"identifier": "3", "value": "{0, 2}"}, {"identifier": "4", "value": "{-1}"}, {"identifier": "5", "value": "{1, -1}"}, {"identifier": "6", "value": "{1, 2}"}, {"identifier": "7", "value": "{0, -1}"}, {"identifier": "8", "value": "{1}"}, {"identifier": "9", "value": "{1, -1}"}, {"identifier": "10", "value": "{0, 2}"}, {"identifier": "11", "value": "{0, 2}"}, {"identifier": "12", "value": "{1}"}, {"identifier": "13", "value": "{1, -1}"}, {"identifier": "14", "value": "{1}"}, {"identifier": "15", "value": "{0, -1}"}, {"identifier": "16", "value": "{2}"}, {"identifier": "17", "value": "{2, -1}"}, {"identifier": "18", "value": "{0}"}, {"identifier": "19", "value": "{0}"}, {"identifier": "20", "value": "{1, 2}"}, {"identifier": "21", "value": "{0, 1}"}, {"identifier": "22", "value": "{1, 2}"}, {"identifier": "23", "value": "{0, 1}"}, {"identifier": "24", "value": "{1}"}], "fitness": "0.6831314919985116", "parents": ["94ce7c4a-2581-4f5e-9223-b6d4bcb1ca7c", "c59729b5-9a0e-4cb0-b9d3-84b01bf6733f"]}, {"uuid": "47cbc9c7-b4b7-4861-8b92-7035c55cab3c", "generation": 10, "genes": [{"identifier": "0", "value": "{1}"}, {"identifier": "1", "value": "{0, 1}"}, {"identifier": "2", "value": "{2}"}, {"identifier": "3", "value": "{0}"}, {"identifier": "4", "value": "{-1}"}, {"identifier": "5", "value": "{1, -1}"}, {"identifier": "6", "value": "{1, 2}"}, {"identifier": "7", "value": "{0, -1}"}, {"identifier": "8", "value": "{1}"}, {"identifier": "9", "value": "{1, -1}"}, {"identifier": "10", "value": "{0, 2}"}, {"identifier": "11", "value": "{0, 2}"}, {"identifier": "12", "value": "{1}"}, {"identifier": "13", "value": "{1, -1}"}, {"identifier": "14", "value": "{1}"}, {"identifier": "15", "value": "{0, -1}"}, {"identifier": "16", "value": "{1, -1}"}, {"identifier": "17", "value": "{2, -1}"}, {"identifier": "18", "value": "{0, -1}"}, {"identifier": "19", "value": "{0}"}, {"identifier": "20", "value": "{1, 2}"}, {"identifier": "21", "value": "{0, 1}"}, {"identifier": "22", "value": "{1, 2}"}, {"identifier": "23", "value": "{0, 1}"}, {"identifier": "24", "value": "{1}"}], "fitness": "0.7145245305962167", "parents": ["c59729b5-9a0e-4cb0-b9d3-84b01bf6733f", "258ac832-1b20-47d4-a02e-7d3e6ff0ed8a"]}, {"uuid": "2dc16786-49ca-400f-b49f-edfbdc43596f", "generation": 8, "genes": [{"identifier": "0", "value": "{1}"}, {"identifier": "1", "value": "{-1}"}, {"identifier": "2", "value": "{2}"}, {"identifier": "3", "value": "{0}"}, {"identifier": "4", "value": "{-1}"}, {"identifier": "5", "value": "{1, -1}"}, {"identifier": "6", "value": "{1}"}, {"identifier": "7", "value": "{0, -1}"}, {"identifier": "8", "value": "{1}"}, {"identifier": "9", "value": "{1, -1}"}, {"identifier": "10", "value": "{0, 2}"}, {"identifier": "11", "value": "{0, 2}"}, {"identifier": "12", "value": "{1}"}, {"identifier": "13", "value": "set()"}, {"identifier": "14", "value": "{1}"}, {"identifier": "15", "value": "{1}"}, {"identifier": "16", "value": "{1, -1}"}, {"identifier": "17", "value": "{-1}"}, {"identifier": "18", "value": "{0, -1}"}, {"identifier": "19", "value": "{0}"}, {"identifier": "20", "value": "{1, 2}"}, {"identifier": "21", "value": "{0, 1}"}, {"identifier": "22", "value": "{1}"}, {"identifier": "23", "value": "{0, 1}"}, {"identifier": "24", "value": "{1}"}], "fitness": "0.6340688009145702", "parents": ["e23871f8-3228-4b0d-bde8-3d05ffa198cc", "6d4be824-942f-4a48-8e9a-039f8b0de6a9"]}], "best": 0.7146903196124822, "average": 0.6699084626314842, "median": 0.6134499576853933, "std": 0.035366408503770444}, {"generation": 10, "goal": "2", "chromosomes": [{"uuid": "555ef073-3248-489b-9791-67aa4a7c1cbc", "generation": 9, "genes": [{"identifier": "0", "value": "{1}"}, {"identifier": "1", "value": "{0, -1}"}, {"identifier": "2", "value": "{-1}"}, {"identifier": "3", "value": "{0, 1}"}, {"identifier": "4", "value": "{0, 1}"}, {"identifier": "5", "value": "{0}"}, {"identifier": "6", "value": "{0, -1}"}, {"identifier": "7", "value": "{0}"}, {"identifier": "8", "value": "{0}"}, {"identifier": "9", "value": "{-1}"}, {"identifier": "10", "value": "{1, -1}"}, {"identifier": "11", "value": "{0, 1}"}, {"identifier": "12", "value": "{1}"}, {"identifier": "13", "value": "{1, 2}"}, {"identifier": "14", "value": "{1, 2}"}, {"identifier": "15", "value": "{1, -1}"}, {"identifier": "16", "value": "{0}"}, {"identifier": "17", "value": "{0}"}, {"identifier": "18", "value": "{0, 1}"}, {"identifier": "19", "value": "{0, 2}"}, {"identifier": "20", "value": "{0, 1}"}, {"identifier": "21", "value": "{0, 1}"}, {"identifier": "22", "value": "{2, -1}"}, {"identifier": "23", "value": "{1}"}, {"identifier": "24", "value": "{1, -1}"}], "fitness": "1.0534287174644272", "parents": ["4a3ac42d-b3e9-4e00-83cf-df607229d36d", "9df74ca6-54ee-411d-82ba-26fde75473fc"]}, {"uuid": "f53e41a7-08ef-4b1d-93f5-1d1efaddd0eb", "generation": 6, "genes": [{"identifier": "0", "value": "{1}"}, {"identifier": "1", "value": "{0, -1}"}, {"identifier": "2", "value": "{-1}"}, {"identifier": "3", "value": "{0, 1}"}, {"identifier": "4", "value": "{0, 1}"}, {"identifier": "5", "value": "{0}"}, {"identifier": "6", "value": "{0}"}, {"identifier": "7", "value": "{0}"}, {"identifier": "8", "value": "{0, -1}"}, {"identifier": "9", "value": "{-1}"}, {"identifier": "10", "value": "{2}"}, {"identifier": "11", "value": "{0, 1}"}, {"identifier": "12", "value": "{1}"}, {"identifier": "13", "value": "{1, 2}"}, {"identifier": "14", "value": "{1, 2}"}, {"identifier": "15", "value": "{1, -1}"}, {"identifier": "16", "value": "{0}"}, {"identifier": "17", "value": "{0, 2}"}, {"identifier": "18", "value": "{0}"}, {"identifier": "19", "value": "{1}"}, {"identifier": "20", "value": "{0, 1}"}, {"identifier": "21", "value": "{0, 1}"}, {"identifier": "22", "value": "{2, -1}"}, {"identifier": "23", "value": "{1}"}, {"identifier": "24", "value": "{1}"}], "fitness": "0.9977524245003913", "parents": ["9d13b327-b0ae-45c1-b176-f4129954f316", "2d34b3ea-cc8a-487f-a429-dd0c9aeede2a"]}, {"uuid": "f4bd1fa2-c84e-43e2-860a-f961ecee4f3c", "generation": 8, "genes": [{"identifier": "0", "value": "{1}"}, {"identifier": "1", "value": "{0, -1}"}, {"identifier": "2", "value": "{-1}"}, {"identifier": "3", "value": "{0, 1}"}, {"identifier": "4", "value": "{0, 1}"}, {"identifier": "5", "value": "{0}"}, {"identifier": "6", "value": "{0, -1}"}, {"identifier": "7", "value": "{0}"}, {"identifier": "8", "value": "{-1}"}, {"identifier": "9", "value": "{-1}"}, {"identifier": "10", "value": "{1, -1}"}, {"identifier": "11", "value": "{0, 1}"}, {"identifier": "12", "value": "{1}"}, {"identifier": "13", "value": "{1, 2}"}, {"identifier": "14", "value": "{1}"}, {"identifier": "15", "value": "{1, 2}"}, {"identifier": "16", "value": "{0}"}, {"identifier": "17", "value": "{0}"}, {"identifier": "18", "value": "{0, 1}"}, {"identifier": "19", "value": "{0, 2}"}, {"identifier": "20", "value": "{0, 1}"}, {"identifier": "21", "value": "{0, 1}"}, {"identifier": "22", "value": "{2, -1}"}, {"identifier": "23", "value": "{2}"}, {"identifier": "24", "value": "{1}"}], "fitness": "0.9995801048391393", "parents": ["4a3ac42d-b3e9-4e00-83cf-df607229d36d", "cffd199b-5c71-4aa8-ad16-0d24112f19fa"]}, {"uuid": "136bc8c7-3a08-44a8-b2e6-6b896b1ddf7c", "generation": 10, "genes": [{"identifier": "0", "value": "{1}"}, {"identifier": "1", "value": "{0, -1}"}, {"identifier": "2", "value": "{-1}"}, {"identifier": "3", "value": "{0, 1}"}, {"identifier": "4", "value": "{0, 1}"}, {"identifier": "5", "value": "{0, -1}"}, {"identifier": "6", "value": "{0, -1}"}, {"identifier": "7", "value": "{0}"}, {"identifier": "8", "value": "{-1}"}, {"identifier": "9", "value": "{-1}"}, {"identifier": "10", "value": "{1, -1}"}, {"identifier": "11", "value": "{0, 1}"}, {"identifier": "12", "value": "{1}"}, {"identifier": "13", "value": "{1, 2}"}, {"identifier": "14", "value": "{1, 2}"}, {"identifier": "15", "value": "{1, -1}"}, {"identifier": "16", "value": "{0}"}, {"identifier": "17", "value": "{0}"}, {"identifier": "18", "value": "{0, 1}"}, {"identifier": "19", "value": "{0, 2}"}, {"identifier": "20", "value": "{0, 1}"}, {"identifier": "21", "value": "{0, 1}"}, {"identifier": "22", "value": "{2}"}, {"identifier": "23", "value": "{1}"}, {"identifier": "24", "value": "{1}"}], "fitness": "1.0180434407855987", "parents": ["e279760f-3138-4f37-a628-d8cf2274c2d8", "e279760f-3138-4f37-a628-d8cf2274c2d8"]}, {"uuid": "f183de03-536a-4c1e-9a77-865730e6f689", "generation": 10, "genes": [{"identifier": "0", "value": "{1}"}, {"identifier": "1", "value": "{0, -1}"}, {"identifier": "2", "value": "{-1}"}, {"identifier": "3", "value": "{0, 1}"}, {"identifier": "4", "value": "{0, 1}"}, {"identifier": "5", "value": "{0}"}, {"identifier": "6", "value": "{0, -1}"}, {"identifier": "7", "value": "{0}"}, {"identifier": "8", "value": "{-1}"}, {"identifier": "9", "value": "{-1}"}, {"identifier": "10", "value": "{1, -1}"}, {"identifier": "11", "value": "{0, 1}"}, {"identifier": "12", "value": "{1}"}, {"identifier": "13", "value": "{1, 2}"}, {"identifier": "14", "value": "{1, 2}"}, {"identifier": "15", "value": "{1, -1}"}, {"identifier": "16", "value": "{0}"}, {"identifier": "17", "value": "{0}"}, {"identifier": "18", "value": "{0, 1}"}, {"identifier": "19", "value": "{0, 2}"}, {"identifier": "20", "value": "{0, 1}"}, {"identifier": "21", "value": "{0, 1}"}, {"identifier": "22", "value": "{2, -1}"}, {"identifier": "23", "value": "{1}"}, {"identifier": "24", "value": "{1}"}], "fitness": "1.0180434407855987", "parents": ["555ef073-3248-489b-9791-67aa4a7c1cbc", "4a3ac42d-b3e9-4e00-83cf-df607229d36d"]}, {"uuid": "61335115-05e9-48ed-8104-2583574fdd0e", "generation": 10, "genes": [{"identifier": "0", "value": "{1}"}, {"identifier": "1", "value": "{0, -1}"}, {"identifier": "2", "value": "{-1}"}, {"identifier": "3", "value": "{0, 1}"}, {"identifier": "4", "value": "{0, 1}"}, {"identifier": "5", "value": "{0}"}, {"identifier": "6", "value": "{0, -1}"}, {"identifier": "7", "value": "{0}"}, {"identifier": "8", "value": "{-1}"}, {"identifier": "9", "value": "{-1}"}, {"identifier": "10", "value": "{1, -1}"}, {"identifier": "11", "value": "{0, 1}"}, {"identifier": "12", "value": "{1}"}, {"identifier": "13", "value": "{1, 2}"}, {"identifier": "14", "value": "{1, 2}"}, {"identifier": "15", "value": "{1, -1}"}, {"identifier": "16", "value": "{0}"}, {"identifier": "17", "value": "{0}"}, {"identifier": "18", "value": "{0, 1}"}, {"identifier": "19", "value": "{0, 2}"}, {"identifier": "20", "value": "{0, 1}"}, {"identifier": "21", "value": "{0, 1}"}, {"identifier": "22", "value": "{2, -1}"}, {"identifier": "23", "value": "{1}"}, {"identifier": "24", "value": "{1}"}], "fitness": "1.0180434407855987", "parents": ["4a3ac42d-b3e9-4e00-83cf-df607229d36d", "e279760f-3138-4f37-a628-d8cf2274c2d8"]}, {"uuid": "e7337e6a-5742-44ec-86f3-0bff68e2074f", "generation": 4, "genes": [{"identifier": "0", "value": "{1}"}, {"identifier": "1", "value": "{1, -1}"}, {"identifier": "2", "value": "{-1}"}, {"identifier": "3", "value": "{0, 1}"}, {"identifier": "4", "value": "{0, 1}"}, {"identifier": "5", "value": "{0}"}, {"identifier": "6", "value": "{0}"}, {"identifier": "7", "value": "{1, 2}"}, {"identifier": "8", "value": "{0}"}, {"identifier": "9", "value": "{-1}"}, {"identifier": "10", "value": "{2}"}, {"identifier": "11", "value": "{0, 1}"}, {"identifier": "12", "value": "{0}"}, {"identifier": "13", "value": "{2}"}, {"identifier": "14", "value": "{1, 2}"}, {"identifier": "15", "value": "{1, 2}"}, {"identifier": "16", "value": "{0}"}, {"identifier": "17", "value": "{0}"}, {"identifier": "18", "value": "{0}"}, {"identifier": "19", "value": "{0, 2}"}, {"identifier": "20", "value": "{0, 1}"}, {"identifier": "21", "value": "{0, -1}"}, {"identifier": "22", "value": "{2, -1}"}, {"identifier": "23", "value": "{1}"}, {"identifier": "24", "value": "{1}"}], "fitness": "0.8755017171984707", "parents": ["35c64f87-ab13-4f7d-9098-0985a0359057", "d18d2a63-bb3d-477a-89e0-71d17db84d58"]}, {"uuid": "4a3ac42d-b3e9-4e00-83cf-df607229d36d", "generation": 7, "genes": [{"identifier": "0", "value": "{1}"}, {"identifier": "1", "value": "{0, -1}"}, {"identifier": "2", "value": "{-1}"}, {"identifier": "3", "value": "{0, 1}"}, {"identifier": "4", "value": "{0, 1}"}, {"identifier": "5", "value": "{0}"}, {"identifier": "6", "value": "{0, -1}"}, {"identifier": "7", "value": "{0}"}, {"identifier": "8", "value": "{-1}"}, {"identifier": "9", "value": "{-1}"}, {"identifier": "10", "value": "{1, -1}"}, {"identifier": "11", "value": "{0, 1}"}, {"identifier": "12", "value": "{1}"}, {"identifier": "13", "value": "{1, 2}"}, {"identifier": "14", "value": "{1, 2}"}, {"identifier": "15", "value": "{1, -1}"}, {"identifier": "16", "value": "{0}"}, {"identifier": "17", "value": "{0}"}, {"identifier": "18", "value": "{0, 1}"}, {"identifier": "19", "value": "{0, 2}"}, {"identifier": "20", "value": "{0, 1}"}, {"identifier": "21", "value": "{0, 1}"}, {"identifier": "22", "value": "{2, -1}"}, {"identifier": "23", "value": "{1}"}, {"identifier": "24", "value": "{1}"}], "fitness": "1.0180434407855987", "parents": ["cffd199b-5c71-4aa8-ad16-0d24112f19fa", "f53e41a7-08ef-4b1d-93f5-1d1efaddd0eb"]}, {"uuid": "c9c8ea77-4f20-4507-a0f8-9a6b8e0686d4", "generation": 10, "genes": [{"identifier": "0", "value": "{1}"}, {"identifier": "1", "value": "{0, -1}"}, {"identifier": "2", "value": "{-1}"}, {"identifier": "3", "value": "{0, 1}"}, {"identifier": "4", "value": "{0, 1}"}, {"identifier": "5", "value": "{0}"}, {"identifier": "6", "value": "{0}"}, {"identifier": "7", "value": "{0}"}, {"identifier": "8", "value": "{0, -1}"}, {"identifier": "9", "value": "{-1}"}, {"identifier": "10", "value": "{2}"}, {"identifier": "11", "value": "{0, 1}"}, {"identifier": "12", "value": "{1}"}, {"identifier": "13", "value": "{1, 2}"}, {"identifier": "14", "value": "{1}"}, {"identifier": "15", "value": "{1, -1}"}, {"identifier": "16", "value": "{0}"}, {"identifier": "17", "value": "{0, 2}"}, {"identifier": "18", "value": "{0, 1}"}, {"identifier": "19", "value": "{0, 2}"}, {"identifier": "20", "value": "{0, 1}"}, {"identifier": "21", "value": "{0, 1}"}, {"identifier": "22", "value": "{2, -1}"}, {"identifier": "23", "value": "{2}"}, {"identifier": "24", "value": "{1}"}], "fitness": "1.0147657272009318", "parents": ["f4bd1fa2-c84e-43e2-860a-f961ecee4f3c", "f53e41a7-08ef-4b1d-93f5-1d1efaddd0eb"]}, {"uuid": "bce6bd68-99d4-4194-9035-2af56ac9160f", "generation": 10, "genes": [{"identifier": "0", "value": "{1}"}, {"identifier": "1", "value": "{0, -1}"}, {"identifier": "2", "value": "{-1}"}, {"identifier": "3", "value": "{0, 1}"}, {"identifier": "4", "value": "{0, 1}"}, {"identifier": "5", "value": "{0}"}, {"identifier": "6", "value": "{0, -1}"}, {"identifier": "7", "value": "{0}"}, {"identifier": "8", "value": "{0}"}, {"identifier": "9", "value": "{-1}"}, {"identifier": "10", "value": "{1, -1}"}, {"identifier": "11", "value": "{0, 1}"}, {"identifier": "12", "value": "{1}"}, {"identifier": "13", "value": "{1, 2}"}, {"identifier": "14", "value": "{1, 2}"}, {"identifier": "15", "value": "{1, -1}"}, {"identifier": "16", "value": "{0}"}, {"identifier": "17", "value": "{0}"}, {"identifier": "18", "value": "{0, 1}"}, {"identifier": "19", "value": "{0, 2}"}, {"identifier": "20", "value": "{0, 1}"}, {"identifier": "21", "value": "{0, 1}"}, {"identifier": "22", "value": "{2, -1}"}, {"identifier": "23", "value": "{1}"}, {"identifier": "24", "value": "{1, -1}"}], "fitness": "1.0534287174644272", "parents": ["555ef073-3248-489b-9791-67aa4a7c1cbc", "4a3ac42d-b3e9-4e00-83cf-df607229d36d"]}, {"uuid": "be8c8e68-45ec-4eb9-b240-e32a3e73b9ab", "generation": 8, "genes": [{"identifier": "0", "value": "{1}"}, {"identifier": "1", "value": "{0, -1}"}, {"identifier": "2", "value": "{-1}"}, {"identifier": "3", "value": "{1}"}, {"identifier": "4", "value": "{0, 1}"}, {"identifier": "5", "value": "{0}"}, {"identifier": "6", "value": "{0}"}, {"identifier": "7", "value": "{0}"}, {"identifier": "8", "value": "{0, -1}"}, {"identifier": "9", "value": "{-1}"}, {"identifier": "10", "value": "{2}"}, {"identifier": "11", "value": "{0, 1}"}, {"identifier": "12", "value": "{1}"}, {"identifier": "13", "value": "{1, 2}"}, {"identifier": "14", "value": "{1, 2}"}, {"identifier": "15", "value": "{1, 2}"}, {"identifier": "16", "value": "{0}"}, {"identifier": "17", "value": "{0, 2}"}, {"identifier": "18", "value": "set()"}, {"identifier": "19", "value": "{1}"}, {"identifier": "20", "value": "{0, 1}"}, {"identifier": "21", "value": "{0, -1}"}, {"identifier": "22", "value": "{2, -1}"}, {"identifier": "23", "value": "{2}"}, {"identifier": "24", "value": "{1}"}], "fitness": "0.8760783911348246", "parents": ["90dbb029-6d7d-40ad-8834-1d7a5b87dabb", "38911bb1-73e4-4c21-b9d3-1d59767ba727"]}], "best": 1.0534287174644272, "average": 0.9947917784495459, "median": 0.8755017171984707, "std": 0.05861490626734347}]}