{"generation": 29, "populations": [{"generation": 29, "goal": "0", "chromosomes": [{"uuid": "2afdd25c-0ae7-437e-b826-172d4eeb0f4e", "generation": 22, "genes": [{"identifier": "0", "value": "set()"}, {"identifier": "1", "value": "{-1}"}, {"identifier": "2", "value": "{-1}"}, {"identifier": "3", "value": "set()"}, {"identifier": "4", "value": "set()"}, {"identifier": "5", "value": "{0, 2}"}, {"identifier": "6", "value": "set()"}, {"identifier": "7", "value": "{0}"}, {"identifier": "8", "value": "{-1}"}], "fitness": "2.0", "parents": ["dcfb0473-b246-4614-bfac-67128ec95015", "dcfb0473-b246-4614-bfac-67128ec95015"]}, {"uuid": "b8442a67-a25c-4f62-bbc8-77392cae6af9", "generation": 29, "genes": [{"identifier": "0", "value": "set()"}, {"identifier": "1", "value": "{-1}"}, {"identifier": "2", "value": "{-1}"}, {"identifier": "3", "value": "set()"}, {"identifier": "4", "value": "set()"}, {"identifier": "5", "value": "{0, 2}"}, {"identifier": "6", "value": "set()"}, {"identifier": "7", "value": "{0}"}, {"identifier": "8", "value": "{-1}"}], "fitness": "2.0", "parents": ["ef4e459d-51dc-4312-898e-288c1bfe7389", "0bf1aeaa-6bbe-4c01-a8a4-a44514cd1d04"]}, {"uuid": "70bcdcba-edc3-4d78-ac10-fbe493edd6d3", "generation": 29, "genes": [{"identifier": "0", "value": "set()"}, {"identifier": "1", "value": "{-1}"}, {"identifier": "2", "value": "{-1}"}, {"identifier": "3", "value": "set()"}, {"identifier": "4", "value": "set()"}, {"identifier": "5", "value": "{0, 2}"}, {"identifier": "6", "value": "set()"}, {"identifier": "7", "value": "{0}"}, {"identifier": "8", "value": "{-1}"}], "fitness": "2.0", "parents": ["0bf1aeaa-6bbe-4c01-a8a4-a44514cd1d04", "ef4e459d-51dc-4312-898e-288c1bfe7389"]}, {"uuid": "ef4e459d-51dc-4312-898e-288c1bfe7389", "generation": 28, "genes": [{"identifier": "0", "value": "set()"}, {"identifier": "1", "value": "{-1}"}, {"identifier": "2", "value": "{-1}"}, {"identifier": "3", "value": "set()"}, {"identifier": "4", "value": "set()"}, {"identifier": "5", "value": "{0, 2}"}, {"identifier": "6", "value": "set()"}, {"identifier": "7", "value": "{0}"}, {"identifier": "8", "value": "{-1}"}], "fitness": "2.0", "parents": ["2afdd25c-0ae7-437e-b826-172d4eeb0f4e", "2afdd25c-0ae7-437e-b826-172d4eeb0f4e"]}, {"uuid": "dd4d0387-ace0-44eb-8b9d-832337d8ce1a", "generation": 29, "genes": [{"identifier": "0", "value": "set()"}, {"identifier": "1", "value": "{-1}"}, {"identifier": "2", "value": "{-1}"}, {"identifier": "3", "value": "set()"}, {"identifier": "4", "value": "set()"}, {"identifier": "5", "value": "{0, 2}"}, {"identifier": "6", "value": "set()"}, {"identifier": "7", "value": "{0}"}, {"identifier": "8", "value": "{-1}"}], "fitness": "2.0", "parents": ["ef4e459d-51dc-4312-898e-288c1bfe7389", "ef4e459d-51dc-4312-898e-288c1bfe7389"]}, {"uuid": "45207123-b68b-4de1-afb6-387ee4f24466", "generation": 29, "genes": [{"identifier": "0", "value": "set()"}, {"identifier": "1", "value": "{-1}"}, {"identifier": "2", "value": "{-1}"}, {"identifier": "3", "value": "set()"}, {"identifier": "4", "value": "set()"}, {"identifier": "5", "value": "{0, 2}"}, {"identifier": "6", "value": "set()"}, {"identifier": "7", "value": "{0}"}, {"identifier": "8", "value": "{-1}"}], "fitness": "2.0", "parents": ["58d82237-4322-47fa-b14f-ce31f8d29175", "2afdd25c-0ae7-437e-b826-172d4eeb0f4e"]}], "average": 2.0, "std": 0.0}, {"generation": 29, "goal": "2", "chromosomes": [{"uuid": "15218099-43d9-42dd-b299-4ae492862e98", "generation": 5, "genes": [{"identifier": "0", "value": "{-1}"}, {"identifier": "1", "value": "{0}"}, {"identifier": "2", "value": "{0, 1}"}, {"identifier": "3", "value": "{0, 1}"}, {"identifier": "4", "value": "set()"}, {"identifier": "5", "value": "set()"}, {"identifier": "6", "value": "set()"}, {"identifier": "7", "value": "set()"}, {"identifier": "8", "value": "{-1}"}], "fitness": "1.6666666666666665", "parents": ["2bf53569-79ad-40d4-a66c-7da0f52910cf", "9ca419e5-c065-424a-b900-a43f598e5aed"]}, {"uuid": "72680121-df41-4b59-851a-42013a31bab2", "generation": 27, "genes": [{"identifier": "0", "value": "{-1}"}, {"identifier": "1", "value": "{0}"}, {"identifier": "2", "value": "{0, 1}"}, {"identifier": "3", "value": "{0, 1}"}, {"identifier": "4", "value": "set()"}, {"identifier": "5", "value": "set()"}, {"identifier": "6", "value": "set()"}, {"identifier": "7", "value": "set()"}, {"identifier": "8", "value": "{-1}"}], "fitness": "1.6666666666666665", "parents": ["8c8cccd4-5519-45a2-9568-be2a2d68ad07", "6d0d6786-db30-499d-9634-1f813aa776ae"]}, {"uuid": "43176b6b-2e7d-43ae-8993-6ab247b516bd", "generation": 29, "genes": [{"identifier": "0", "value": "{-1}"}, {"identifier": "1", "value": "{0}"}, {"identifier": "2", "value": "{0, 1}"}, {"identifier": "3", "value": "{0}"}, {"identifier": "4", "value": "set()"}, {"identifier": "5", "value": "set()"}, {"identifier": "6", "value": "set()"}, {"identifier": "7", "value": "set()"}, {"identifier": "8", "value": "{-1}"}], "fitness": "1.6666666666666665", "parents": ["48ef1dcb-049c-44e5-b412-1cfb88d23c63", "6d0d6786-db30-499d-9634-1f813aa776ae"]}, {"uuid": "6d0d6786-db30-499d-9634-1f813aa776ae", "generation": 26, "genes": [{"identifier": "0", "value": "{-1}"}, {"identifier": "1", "value": "{0}"}, {"identifier": "2", "value": "{0, 1}"}, {"identifier": "3", "value": "{0, 1}"}, {"identifier": "4", "value": "set()"}, {"identifier": "5", "value": "set()"}, {"identifier": "6", "value": "set()"}, {"identifier": "7", "value": "set()"}, {"identifier": "8", "value": "{-1}"}], "fitness": "1.6666666666666665", "parents": ["fbbea339-197a-4582-a19e-2db8f49603bc", "66b45e7d-4b73-4740-9cd3-7f17383b426c"]}, {"uuid": "668dd97a-5c49-4456-9cf0-7c64a62379ed", "generation": 27, "genes": [{"identifier": "0", "value": "{-1}"}, {"identifier": "1", "value": "{0}"}, {"identifier": "2", "value": "{0, 1}"}, {"identifier": "3", "value": "{0, 1}"}, {"identifier": "4", "value": "set()"}, {"identifier": "5", "value": "set()"}, {"identifier": "6", "value": "set()"}, {"identifier": "7", "value": "set()"}, {"identifier": "8", "value": "{-1}"}], "fitness": "1.6666666666666665", "parents": ["8c8cccd4-5519-45a2-9568-be2a2d68ad07", "8c8cccd4-5519-45a2-9568-be2a2d68ad07"]}, {"uuid": "ba70aa78-a5f8-4685-adbd-3716af382db0", "generation": 29, "genes": [{"identifier": "0", "value": "set()"}, {"identifier": "1", "value": "{0}"}, {"identifier": "2", "value": "{0, 1}"}, {"identifier": "3", "value": "{0, 1}"}, {"identifier": "4", "value": "set()"}, {"identifier": "5", "value": "set()"}, {"identifier": "6", "value": "set()"}, {"identifier": "7", "value": "set()"}, {"identifier": "8", "value": "{-1}"}], "fitness": "1.6666666666666665", "parents": ["784d0783-5e40-4f41-9138-50136d5a477a", "6d0d6786-db30-499d-9634-1f813aa776ae"]}], "average": 1.6666666666666663, "std": 2.220446049250313e-16}, {"generation": 29, "goal": "1", "chromosomes": [{"uuid": "1cd554ef-cd92-48e3-a1bb-f848c53c021c", "generation": 13, "genes": [{"identifier": "0", "value": "set()"}, {"identifier": "1", "value": "set()"}, {"identifier": "2", "value": "set()"}, {"identifier": "3", "value": "{-1}"}, {"identifier": "4", "value": "set()"}, {"identifier": "5", "value": "{1, 2}"}, {"identifier": "6", "value": "set()"}, {"identifier": "7", "value": "{1}"}, {"identifier": "8", "value": "set()"}], "fitness": "2.0", "parents": ["8c022cd1-b7f3-4058-9803-a47c53d9c0bf", "2be6218f-b1a3-4119-baab-39d55d9777cf"]}, {"uuid": "b8a33470-2a91-4e6a-a92a-0ac25520d5a5", "generation": 29, "genes": [{"identifier": "0", "value": "set()"}, {"identifier": "1", "value": "set()"}, {"identifier": "2", "value": "set()"}, {"identifier": "3", "value": "{-1}"}, {"identifier": "4", "value": "set()"}, {"identifier": "5", "value": "{1, 2}"}, {"identifier": "6", "value": "set()"}, {"identifier": "7", "value": "{1}"}, {"identifier": "8", "value": "set()"}], "fitness": "2.0", "parents": ["8e2a0198-3310-4fe1-968a-8b50b420839a", "1cd554ef-cd92-48e3-a1bb-f848c53c021c"]}, {"uuid": "3dd811ed-91b6-4633-be2c-821e1b4e2897", "generation": 28, "genes": [{"identifier": "0", "value": "set()"}, {"identifier": "1", "value": "set()"}, {"identifier": "2", "value": "set()"}, {"identifier": "3", "value": "{-1}"}, {"identifier": "4", "value": "set()"}, {"identifier": "5", "value": "{1, 2}"}, {"identifier": "6", "value": "set()"}, {"identifier": "7", "value": "{1}"}, {"identifier": "8", "value": "set()"}], "fitness": "2.0", "parents": ["a9d55e13-8e18-4913-98ba-64bd41f328c5", "1cd554ef-cd92-48e3-a1bb-f848c53c021c"]}, {"uuid": "5043bfa2-99f7-410f-97af-c3fec3e6f4d7", "generation": 29, "genes": [{"identifier": "0", "value": "set()"}, {"identifier": "1", "value": "set()"}, {"identifier": "2", "value": "set()"}, {"identifier": "3", "value": "{-1}"}, {"identifier": "4", "value": "set()"}, {"identifier": "5", "value": "{1, 2}"}, {"identifier": "6", "value": "set()"}, {"identifier": "7", "value": "set()"}, {"identifier": "8", "value": "set()"}], "fitness": "2.0", "parents": ["6cc55bf4-b641-46fb-a88c-1e08f1382cfd", "6cc55bf4-b641-46fb-a88c-1e08f1382cfd"]}, {"uuid": "8e2a0198-3310-4fe1-968a-8b50b420839a", "generation": 28, "genes": [{"identifier": "0", "value": "set()"}, {"identifier": "1", "value": "set()"}, {"identifier": "2", "value": "set()"}, {"identifier": "3", "value": "{-1}"}, {"identifier": "4", "value": "set()"}, {"identifier": "5", "value": "{1}"}, {"identifier": "6", "value": "set()"}, {"identifier": "7", "value": "{1}"}, {"identifier": "8", "value": "set()"}], "fitness": "2.0", "parents": ["1cd554ef-cd92-48e3-a1bb-f848c53c021c", "592eb95c-e7c8-4c50-a7f5-84a0663c02c3"]}, {"uuid": "1b004491-06fc-4092-a0ca-599f5cc71cae", "generation": 29, "genes": [{"identifier": "0", "value": "set()"}, {"identifier": "1", "value": "set()"}, {"identifier": "2", "value": "set()"}, {"identifier": "3", "value": "set()"}, {"identifier": "4", "value": "set()"}, {"identifier": "5", "value": "{1}"}, {"identifier": "6", "value": "set()"}, {"identifier": "7", "value": "{1}"}, {"identifier": "8", "value": "set()"}], "fitness": "2.0", "parents": ["a9d55e13-8e18-4913-98ba-64bd41f328c5", "7da0521b-e473-4374-851d-dacfc63c8209"]}], "average": 2.0, "std": 0.0}]}