{"generation": 67, "populations": [{"generation": 67, "goal": "1", "chromosomes": [{"uuid": "f73b5700-3215-4067-8b37-de57ed9f2e68", "generation": 41, "genes": [{"identifier": "0", "value": "set()"}, {"identifier": "1", "value": "set()"}, {"identifier": "2", "value": "{-1}"}, {"identifier": "3", "value": "{-1}"}, {"identifier": "4", "value": "{0}"}, {"identifier": "5", "value": "set()"}, {"identifier": "6", "value": "set()"}, {"identifier": "7", "value": "{-1}"}, {"identifier": "8", "value": "{-1}"}], "fitness": "1.0", "parents": ["42cdd9f4-de2c-4840-9101-5aeefe42f861", "492bef2c-868b-4810-a4da-47a8350a609a"]}, {"uuid": "81cb908e-9004-491a-94aa-e978c19d99ca", "generation": 65, "genes": [{"identifier": "0", "value": "set()"}, {"identifier": "1", "value": "set()"}, {"identifier": "2", "value": "{-1}"}, {"identifier": "3", "value": "{-1}"}, {"identifier": "4", "value": "{0}"}, {"identifier": "5", "value": "set()"}, {"identifier": "6", "value": "set()"}, {"identifier": "7", "value": "{-1}"}, {"identifier": "8", "value": "{-1}"}], "fitness": "1.0", "parents": ["9c0e6164-a377-4733-9772-37ce4d8f4d6a", "80c2ab83-8018-41c6-9bf2-6fa84078ebfc"]}, {"uuid": "16c742e1-3fa8-4370-9d3f-f55f98c5f9a1", "generation": 67, "genes": [{"identifier": "0", "value": "set()"}, {"identifier": "1", "value": "set()"}, {"identifier": "2", "value": "{-1}"}, {"identifier": "3", "value": "{-1}"}, {"identifier": "4", "value": "set()"}, {"identifier": "5", "value": "set()"}, {"identifier": "6", "value": "set()"}, {"identifier": "7", "value": "{-1}"}, {"identifier": "8", "value": "set()"}], "fitness": "0.0", "parents": ["365cf0d9-36f5-4cf0-a943-b0f80cbe267a", "3314c9aa-b1e8-4930-8e16-3261b039ae8a"]}, {"uuid": "54999f2b-f183-4ab7-b95e-507bbbbb7e97", "generation": 64, "genes": [{"identifier": "0", "value": "set()"}, {"identifier": "1", "value": "set()"}, {"identifier": "2", "value": "{-1}"}, {"identifier": "3", "value": "{-1}"}, {"identifier": "4", "value": "{0}"}, {"identifier": "5", "value": "set()"}, {"identifier": "6", "value": "set()"}, {"identifier": "7", "value": "{-1}"}, {"identifier": "8", "value": "set()"}], "fitness": "1.0", "parents": ["8b027a63-0123-4c67-9a4b-7f34160bdd9b", "80c2ab83-8018-41c6-9bf2-6fa84078ebfc"]}, {"uuid": "d04bc97e-9f68-4f9b-95cf-0d941c8c86f6", "generation": 67, "genes": [{"identifier": "0", "value": "set()"}, {"identifier": "1", "value": "set()"}, {"identifier": "2", "value": "set()"}, {"identifier": "3", "value": "{-1}"}, {"identifier": "4", "value": "{0}"}, {"identifier": "5", "value": "set()"}, {"identifier": "6", "value": "set()"}, {"identifier": "7", "value": "{-1}"}, {"identifier": "8", "value": "set()"}], "fitness": "1.0", "parents": ["ad135038-7768-4db3-b250-558d2866a867", "db2b04eb-8cf3-4816-a2f2-d37f6db63c2a"]}, {"uuid": "8b027a63-0123-4c67-9a4b-7f34160bdd9b", "generation": 61, "genes": [{"identifier": "0", "value": "set()"}, {"identifier": "1", "value": "set()"}, {"identifier": "2", "value": "{-1}"}, {"identifier": "3", "value": "{-1}"}, {"identifier": "4", "value": "{0}"}, {"identifier": "5", "value": "set()"}, {"identifier": "6", "value": "set()"}, {"identifier": "7", "value": "{-1}"}, {"identifier": "8", "value": "set()"}], "fitness": "1.0", "parents": ["21ec41c3-670b-46aa-b7b7-11c8a16e2b63", "48d7bf24-a43a-45bf-aace-8c25fd87496d"]}, {"uuid": "88e8c546-7c0b-4956-83dd-b3f094b806fe", "generation": 65, "genes": [{"identifier": "0", "value": "set()"}, {"identifier": "1", "value": "set()"}, {"identifier": "2", "value": "{-1}"}, {"identifier": "3", "value": "{-1}"}, {"identifier": "4", "value": "{0}"}, {"identifier": "5", "value": "set()"}, {"identifier": "6", "value": "set()"}, {"identifier": "7", "value": "{-1}"}, {"identifier": "8", "value": "set()"}], "fitness": "1.0", "parents": ["4452da5a-1d70-4de8-bd83-e93a8a05602f", "5f353ef5-f598-4392-b580-c4cea1b4b295"]}, {"uuid": "9be65496-0b0c-4283-a8e7-1b37ef1475e7", "generation": 65, "genes": [{"identifier": "0", "value": "set()"}, {"identifier": "1", "value": "set()"}, {"identifier": "2", "value": "{-1}"}, {"identifier": "3", "value": "{-1}"}, {"identifier": "4", "value": "{0}"}, {"identifier": "5", "value": "set()"}, {"identifier": "6", "value": "set()"}, {"identifier": "7", "value": "{-1}"}, {"identifier": "8", "value": "set()"}], "fitness": "1.0", "parents": ["e51b1471-84c7-45ca-8b7f-52c00b52007b", "365cf0d9-36f5-4cf0-a943-b0f80cbe267a"]}, {"uuid": "2a4977a5-9c3d-46ec-850e-9eeed20ee734", "generation": 67, "genes": [{"identifier": "0", "value": "set()"}, {"identifier": "1", "value": "set()"}, {"identifier": "2", "value": "set()"}, {"identifier": "3", "value": "{-1}"}, {"identifier": "4", "value": "{0}"}, {"identifier": "5", "value": "set()"}, {"identifier": "6", "value": "set()"}, {"identifier": "7", "value": "{-1}"}, {"identifier": "8", "value": "set()"}], "fitness": "1.0", "parents": ["9c0e6164-a377-4733-9772-37ce4d8f4d6a", "ad135038-7768-4db3-b250-558d2866a867"]}, {"uuid": "a47f3c54-de10-4961-8fe6-d2eb1776846a", "generation": 67, "genes": [{"identifier": "0", "value": "set()"}, {"identifier": "1", "value": "set()"}, {"identifier": "2", "value": "{-1}"}, {"identifier": "3", "value": "set()"}, {"identifier": "4", "value": "{0}"}, {"identifier": "5", "value": "set()"}, {"identifier": "6", "value": "set()"}, {"identifier": "7", "value": "{-1}"}, {"identifier": "8", "value": "set()"}], "fitness": "1.0", "parents": ["365cf0d9-36f5-4cf0-a943-b0f80cbe267a", "365cf0d9-36f5-4cf0-a943-b0f80cbe267a"]}, {"uuid": "365cf0d9-36f5-4cf0-a943-b0f80cbe267a", "generation": 64, "genes": [{"identifier": "0", "value": "set()"}, {"identifier": "1", "value": "set()"}, {"identifier": "2", "value": "{-1}"}, {"identifier": "3", "value": "set()"}, {"identifier": "4", "value": "{0}"}, {"identifier": "5", "value": "set()"}, {"identifier": "6", "value": "set()"}, {"identifier": "7", "value": "{-1}"}, {"identifier": "8", "value": "set()"}], "fitness": "1.0", "parents": ["a216a445-7a14-486f-bbae-e154274a7a45", "be699bd6-c21e-4abe-9ab0-03f131eadaef"]}, {"uuid": "9b8de85b-538c-4ada-99a6-8503c7d342bc", "generation": 63, "genes": [{"identifier": "0", "value": "set()"}, {"identifier": "1", "value": "set()"}, {"identifier": "2", "value": "set()"}, {"identifier": "3", "value": "{-1}"}, {"identifier": "4", "value": "{0}"}, {"identifier": "5", "value": "set()"}, {"identifier": "6", "value": "set()"}, {"identifier": "7", "value": "{-1}"}, {"identifier": "8", "value": "set()"}], "fitness": "1.0", "parents": ["20b63e45-f9d1-4036-bbe0-05350b65c9a6", "c2bfd7d8-1b04-4470-8870-e615fe687f67"]}, {"uuid": "f3c40738-5c53-4f2b-9c8f-471e31b4371c", "generation": 67, "genes": [{"identifier": "0", "value": "set()"}, {"identifier": "1", "value": "set()"}, {"identifier": "2", "value": "{-1}"}, {"identifier": "3", "value": "{-1}"}, {"identifier": "4", "value": "{0}"}, {"identifier": "5", "value": "set()"}, {"identifier": "6", "value": "set()"}, {"identifier": "7", "value": "{-1}"}, {"identifier": "8", "value": "{-1}"}], "fitness": "1.0", "parents": ["81cb908e-9004-491a-94aa-e978c19d99ca", "30299ea4-3253-400a-b1de-773a9405c77b"]}, {"uuid": "db2b04eb-8cf3-4816-a2f2-d37f6db63c2a", "generation": 66, "genes": [{"identifier": "0", "value": "set()"}, {"identifier": "1", "value": "set()"}, {"identifier": "2", "value": "set()"}, {"identifier": "3", "value": "{-1}"}, {"identifier": "4", "value": "{0}"}, {"identifier": "5", "value": "set()"}, {"identifier": "6", "value": "set()"}, {"identifier": "7", "value": "{-1}"}, {"identifier": "8", "value": "set()"}], "fitness": "1.0", "parents": ["1986e005-858c-4b56-99e1-602fe69fcdae", "a216a445-7a14-486f-bbae-e154274a7a45"]}, {"uuid": "30299ea4-3253-400a-b1de-773a9405c77b", "generation": 66, "genes": [{"identifier": "0", "value": "set()"}, {"identifier": "1", "value": "set()"}, {"identifier": "2", "value": "{-1}"}, {"identifier": "3", "value": "{-1}"}, {"identifier": "4", "value": "{0}"}, {"identifier": "5", "value": "set()"}, {"identifier": "6", "value": "set()"}, {"identifier": "7", "value": "{-1}"}, {"identifier": "8", "value": "{-1}"}], "fitness": "1.0", "parents": ["9c0e6164-a377-4733-9772-37ce4d8f4d6a", "5e5eb924-077b-4d71-a223-0dae2ec830e3"]}, {"uuid": "2ca7eb81-7dd8-428e-8600-f6a0b3eb3f65", "generation": 67, "genes": [{"identifier": "0", "value": "set()"}, {"identifier": "1", "value": "set()"}, {"identifier": "2", "value": "{-1}"}, {"identifier": "3", "value": "set()"}, {"identifier": "4", "value": "{0}"}, {"identifier": "5", "value": "set()"}, {"identifier": "6", "value": "set()"}, {"identifier": "7", "value": "{-1}"}, {"identifier": "8", "value": "set()"}], "fitness": "1.0", "parents": ["365cf0d9-36f5-4cf0-a943-b0f80cbe267a", "365cf0d9-36f5-4cf0-a943-b0f80cbe267a"]}, {"uuid": "9657798c-137b-41cd-8f4c-ca71ba7ebb21", "generation": 65, "genes": [{"identifier": "0", "value": "set()"}, {"identifier": "1", "value": "set()"}, {"identifier": "2", "value": "{-1}"}, {"identifier": "3", "value": "{-1}"}, {"identifier": "4", "value": "{0}"}, {"identifier": "5", "value": "set()"}, {"identifier": "6", "value": "set()"}, {"identifier": "7", "value": "{-1}"}, {"identifier": "8", "value": "set()"}], "fitness": "1.0", "parents": ["9c0e6164-a377-4733-9772-37ce4d8f4d6a", "80c2ab83-8018-41c6-9bf2-6fa84078ebfc"]}, {"uuid": "39016a63-dee2-40c6-a8b0-c0307293dd02", "generation": 66, "genes": [{"identifier": "0", "value": "set()"}, {"identifier": "1", "value": "set()"}, {"identifier": "2", "value": "{-1}"}, {"identifier": "3", "value": "{-1}"}, {"identifier": "4", "value": "{0}"}, {"identifier": "5", "value": "set()"}, {"identifier": "6", "value": "set()"}, {"identifier": "7", "value": "{-1}"}, {"identifier": "8", "value": "{-1}"}], "fitness": "1.0", "parents": ["81cb908e-9004-491a-94aa-e978c19d99ca", "9be65496-0b0c-4283-a8e7-1b37ef1475e7"]}, {"uuid": "d51f8192-4e28-46d8-8569-38bdc0092246", "generation": 67, "genes": [{"identifier": "0", "value": "set()"}, {"identifier": "1", "value": "set()"}, {"identifier": "2", "value": "{-1}"}, {"identifier": "3", "value": "{-1}"}, {"identifier": "4", "value": "{0}"}, {"identifier": "5", "value": "set()"}, {"identifier": "6", "value": "set()"}, {"identifier": "7", "value": "{-1}"}, {"identifier": "8", "value": "set()"}], "fitness": "1.0", "parents": ["9c0e6164-a377-4733-9772-37ce4d8f4d6a", "ad135038-7768-4db3-b250-558d2866a867"]}, {"uuid": "50b8e357-67a8-4dab-b482-64e353ff804e", "generation": 65, "genes": [{"identifier": "0", "value": "set()"}, {"identifier": "1", "value": "set()"}, {"identifier": "2", "value": "{-1}"}, {"identifier": "3", "value": "{-1}"}, {"identifier": "4", "value": "{0}"}, {"identifier": "5", "value": "set()"}, {"identifier": "6", "value": "set()"}, {"identifier": "7", "value": "{-1}"}, {"identifier": "8", "value": "set()"}], "fitness": "1.0", "parents": ["4452da5a-1d70-4de8-bd83-e93a8a05602f", "5f353ef5-f598-4392-b580-c4cea1b4b295"]}, {"uuid": "ad135038-7768-4db3-b250-558d2866a867", "generation": 66, "genes": [{"identifier": "0", "value": "set()"}, {"identifier": "1", "value": "set()"}, {"identifier": "2", "value": "set()"}, {"identifier": "3", "value": "{-1}"}, {"identifier": "4", "value": "{0}"}, {"identifier": "5", "value": "set()"}, {"identifier": "6", "value": "set()"}, {"identifier": "7", "value": "{-1}"}, {"identifier": "8", "value": "set()"}], "fitness": "1.0", "parents": ["8b027a63-0123-4c67-9a4b-7f34160bdd9b", "9b8de85b-538c-4ada-99a6-8503c7d342bc"]}], "best": 1.0, "average": 0.9523809523809523, "median": 1.0, "std": 0.21295885499998005}, {"generation": 67, "goal": "0", "chromosomes": [{"uuid": "03458a3b-e25d-4f74-a723-54d366b9e167", "generation": 18, "genes": [{"identifier": "0", "value": "set()"}, {"identifier": "1", "value": "{-1}"}, {"identifier": "2", "value": "set()"}, {"identifier": "3", "value": "set()"}, {"identifier": "4", "value": "{2}"}, {"identifier": "5", "value": "{-1}"}, {"identifier": "6", "value": "{-1}"}, {"identifier": "7", "value": "set()"}, {"identifier": "8", "value": "set()"}], "fitness": "1.0", "parents": ["876e3b48-5f69-4788-8ac5-61da04d623cc", "0595a2d7-88bf-4455-838d-05a888790728"]}, {"uuid": "788a2f8b-daa2-4aa6-b171-2dfcab6169ab", "generation": 67, "genes": [{"identifier": "0", "value": "set()"}, {"identifier": "1", "value": "{-1}"}, {"identifier": "2", "value": "set()"}, {"identifier": "3", "value": "set()"}, {"identifier": "4", "value": "{2}"}, {"identifier": "5", "value": "{-1}"}, {"identifier": "6", "value": "{-1}"}, {"identifier": "7", "value": "set()"}, {"identifier": "8", "value": "set()"}], "fitness": "1.0", "parents": ["e9185bf0-80e6-472c-98c9-fb76cdd00b7a", "37d51b5d-4f59-45ad-a31f-d7472d3ec0c6"]}, {"uuid": "3c97e68b-1048-4e5f-9c30-8c6a2939faad", "generation": 64, "genes": [{"identifier": "0", "value": "set()"}, {"identifier": "1", "value": "{-1}"}, {"identifier": "2", "value": "set()"}, {"identifier": "3", "value": "set()"}, {"identifier": "4", "value": "{2}"}, {"identifier": "5", "value": "set()"}, {"identifier": "6", "value": "{-1}"}, {"identifier": "7", "value": "set()"}, {"identifier": "8", "value": "set()"}], "fitness": "1.0", "parents": ["e54aae3c-838d-48ec-a37a-4dd69ef13c0f", "ef3ea5a4-1e50-477c-947d-20baf35b0b7a"]}, {"uuid": "71c55de1-565a-4200-9d8c-ce5b0ddfce88", "generation": 65, "genes": [{"identifier": "0", "value": "set()"}, {"identifier": "1", "value": "set()"}, {"identifier": "2", "value": "set()"}, {"identifier": "3", "value": "set()"}, {"identifier": "4", "value": "{2}"}, {"identifier": "5", "value": "{-1}"}, {"identifier": "6", "value": "{-1}"}, {"identifier": "7", "value": "set()"}, {"identifier": "8", "value": "set()"}], "fitness": "1.0", "parents": ["6223ee1f-b714-4d60-bc58-706fb41a2c69", "c63a2042-3ed6-4a21-be3a-dfaf0a3c9cd9"]}, {"uuid": "644ca114-8f6f-455d-93b8-30851dd9cf50", "generation": 67, "genes": [{"identifier": "0", "value": "set()"}, {"identifier": "1", "value": "{-1}"}, {"identifier": "2", "value": "set()"}, {"identifier": "3", "value": "set()"}, {"identifier": "4", "value": "{2}"}, {"identifier": "5", "value": "{-1}"}, {"identifier": "6", "value": "{-1}"}, {"identifier": "7", "value": "set()"}, {"identifier": "8", "value": "set()"}], "fitness": "1.0", "parents": ["816ddab1-c722-438a-9301-573aa92c1506", "251d3579-6c7d-4502-90f2-4c0179207d7d"]}, {"uuid": "80008bb5-9ac7-4ce9-ab0d-63258eba7e02", "generation": 62, "genes": [{"identifier": "0", "value": "set()"}, {"identifier": "1", "value": "{-1}"}, {"identifier": "2", "value": "set()"}, {"identifier": "3", "value": "set()"}, {"identifier": "4", "value": "{2}"}, {"identifier": "5", "value": "{-1}"}, {"identifier": "6", "value": "{-1}"}, {"identifier": "7", "value": "set()"}, {"identifier": "8", "value": "set()"}], "fitness": "1.0", "parents": ["03458a3b-e25d-4f74-a723-54d366b9e167", "2dc9a260-fd63-4772-b1e0-c8a9b90cd149"]}, {"uuid": "c6015deb-c9ba-49c3-9ca3-c34f6751a75d", "generation": 66, "genes": [{"identifier": "0", "value": "set()"}, {"identifier": "1", "value": "{-1}"}, {"identifier": "2", "value": "set()"}, {"identifier": "3", "value": "set()"}, {"identifier": "4", "value": "{2}"}, {"identifier": "5", "value": "{-1}"}, {"identifier": "6", "value": "{-1}"}, {"identifier": "7", "value": "set()"}, {"identifier": "8", "value": "set()"}], "fitness": "1.0", "parents": ["664b0954-c42a-4db8-80d2-96444c1ce709", "5c258bb4-8330-4b27-b7df-0189a36084df"]}, {"uuid": "2d7a127e-8417-40a6-8748-5683d44bb53b", "generation": 65, "genes": [{"identifier": "0", "value": "set()"}, {"identifier": "1", "value": "set()"}, {"identifier": "2", "value": "set()"}, {"identifier": "3", "value": "set()"}, {"identifier": "4", "value": "{2}"}, {"identifier": "5", "value": "{-1}"}, {"identifier": "6", "value": "set()"}, {"identifier": "7", "value": "set()"}, {"identifier": "8", "value": "set()"}], "fitness": "1.0", "parents": ["6223ee1f-b714-4d60-bc58-706fb41a2c69", "c63a2042-3ed6-4a21-be3a-dfaf0a3c9cd9"]}, {"uuid": "8dad5d8d-cf50-4144-b517-336bc1aa2559", "generation": 59, "genes": [{"identifier": "0", "value": "set()"}, {"identifier": "1", "value": "{-1}"}, {"identifier": "2", "value": "set()"}, {"identifier": "3", "value": "set()"}, {"identifier": "4", "value": "{2}"}, {"identifier": "5", "value": "{-1}"}, {"identifier": "6", "value": "{-1}"}, {"identifier": "7", "value": "set()"}, {"identifier": "8", "value": "set()"}], "fitness": "1.0", "parents": ["dbe2fe6d-5a26-4f0d-b0aa-72413a1a505b", "dd345476-2d7d-48cb-a491-00fbd9bacc8c"]}, {"uuid": "85902d51-8b30-428a-8d32-c503f08b67c5", "generation": 63, "genes": [{"identifier": "0", "value": "set()"}, {"identifier": "1", "value": "{-1}"}, {"identifier": "2", "value": "set()"}, {"identifier": "3", "value": "set()"}, {"identifier": "4", "value": "{2}"}, {"identifier": "5", "value": "{-1}"}, {"identifier": "6", "value": "{-1}"}, {"identifier": "7", "value": "set()"}, {"identifier": "8", "value": "set()"}], "fitness": "1.0", "parents": ["b344d3c2-d74b-44ff-97d6-96c3b0335896", "1085f00b-46df-4112-bfff-20b51cbc1d84"]}, {"uuid": "f481ce49-df02-4908-8d7e-0a61692eee3f", "generation": 67, "genes": [{"identifier": "0", "value": "set()"}, {"identifier": "1", "value": "{-1}"}, {"identifier": "2", "value": "set()"}, {"identifier": "3", "value": "set()"}, {"identifier": "4", "value": "{2}"}, {"identifier": "5", "value": "{-1}"}, {"identifier": "6", "value": "{-1}"}, {"identifier": "7", "value": "set()"}, {"identifier": "8", "value": "set()"}], "fitness": "1.0", "parents": ["03458a3b-e25d-4f74-a723-54d366b9e167", "c6015deb-c9ba-49c3-9ca3-c34f6751a75d"]}, {"uuid": "a0efcc52-0833-49c2-9c36-e829f211d6bb", "generation": 64, "genes": [{"identifier": "0", "value": "set()"}, {"identifier": "1", "value": "set()"}, {"identifier": "2", "value": "set()"}, {"identifier": "3", "value": "set()"}, {"identifier": "4", "value": "set()"}, {"identifier": "5", "value": "{-1}"}, {"identifier": "6", "value": "{-1}"}, {"identifier": "7", "value": "set()"}, {"identifier": "8", "value": "set()"}], "fitness": "0.0", "parents": ["e74e7c5f-c1bb-4abd-b875-4eeeacf035be", "e74e7c5f-c1bb-4abd-b875-4eeeacf035be"]}, {"uuid": "664b0954-c42a-4db8-80d2-96444c1ce709", "generation": 57, "genes": [{"identifier": "0", "value": "set()"}, {"identifier": "1", "value": "set()"}, {"identifier": "2", "value": "set()"}, {"identifier": "3", "value": "set()"}, {"identifier": "4", "value": "{2}"}, {"identifier": "5", "value": "set()"}, {"identifier": "6", "value": "{-1}"}, {"identifier": "7", "value": "set()"}, {"identifier": "8", "value": "set()"}], "fitness": "1.0", "parents": ["828a03a3-3cca-416a-9232-1ef69307645b", "68655e80-ea40-4f73-a040-ef31dba26d6a"]}, {"uuid": "056c4190-4955-4a8f-a6ce-4512136a7f87", "generation": 67, "genes": [{"identifier": "0", "value": "set()"}, {"identifier": "1", "value": "{-1}"}, {"identifier": "2", "value": "set()"}, {"identifier": "3", "value": "set()"}, {"identifier": "4", "value": "{2}"}, {"identifier": "5", "value": "set()"}, {"identifier": "6", "value": "{-1}"}, {"identifier": "7", "value": "set()"}, {"identifier": "8", "value": "set()"}], "fitness": "1.0", "parents": ["e9185bf0-80e6-472c-98c9-fb76cdd00b7a", "37d51b5d-4f59-45ad-a31f-d7472d3ec0c6"]}, {"uuid": "f94a1f79-c642-4951-84ba-68400457ce7a", "generation": 67, "genes": [{"identifier": "0", "value": "set()"}, {"identifier": "1", "value": "{-1}"}, {"identifier": "2", "value": "set()"}, {"identifier": "3", "value": "set()"}, {"identifier": "4", "value": "{2}"}, {"identifier": "5", "value": "{-1}"}, {"identifier": "6", "value": "{-1}"}, {"identifier": "7", "value": "set()"}, {"identifier": "8", "value": "set()"}], "fitness": "1.0", "parents": ["03458a3b-e25d-4f74-a723-54d366b9e167", "c6015deb-c9ba-49c3-9ca3-c34f6751a75d"]}, {"uuid": "988d5d2b-ca21-4e39-8559-c98ea58d6e36", "generation": 67, "genes": [{"identifier": "0", "value": "set()"}, {"identifier": "1", "value": "set()"}, {"identifier": "2", "value": "set()"}, {"identifier": "3", "value": "set()"}, {"identifier": "4", "value": "{2}"}, {"identifier": "5", "value": "{-1}"}, {"identifier": "6", "value": "set()"}, {"identifier": "7", "value": "set()"}, {"identifier": "8", "value": "set()"}], "fitness": "1.0", "parents": ["2d7a127e-8417-40a6-8748-5683d44bb53b", "e9185bf0-80e6-472c-98c9-fb76cdd00b7a"]}, {"uuid": "816ddab1-c722-438a-9301-573aa92c1506", "generation": 64, "genes": [{"identifier": "0", "value": "set()"}, {"identifier": "1", "value": "{-1}"}, {"identifier": "2", "value": "set()"}, {"identifier": "3", "value": "set()"}, {"identifier": "4", "value": "{2}"}, {"identifier": "5", "value": "{-1}"}, {"identifier": "6", "value": "{-1}"}, {"identifier": "7", "value": "set()"}, {"identifier": "8", "value": "set()"}], "fitness": "1.0", "parents": ["e54aae3c-838d-48ec-a37a-4dd69ef13c0f", "32d49a83-1fc8-42a4-9384-3ae4a96039e7"]}, {"uuid": "37d51b5d-4f59-45ad-a31f-d7472d3ec0c6", "generation": 64, "genes": [{"identifier": "0", "value": "set()"}, {"identifier": "1", "value": "{-1}"}, {"identifier": "2", "value": "set()"}, {"identifier": "3", "value": "set()"}, {"identifier": "4", "value": "{2}"}, {"identifier": "5", "value": "set()"}, {"identifier": "6", "value": "{-1}"}, {"identifier": "7", "value": "set()"}, {"identifier": "8", "value": "set()"}], "fitness": "1.0", "parents": ["ef3ea5a4-1e50-477c-947d-20baf35b0b7a", "54958f42-ff41-4b6d-9582-ac3fba28d8e3"]}, {"uuid": "6223ee1f-b714-4d60-bc58-706fb41a2c69", "generation": 62, "genes": [{"identifier": "0", "value": "set()"}, {"identifier": "1", "value": "set()"}, {"identifier": "2", "value": "set()"}, {"identifier": "3", "value": "set()"}, {"identifier": "4", "value": "{2}"}, {"identifier": "5", "value": "{-1}"}, {"identifier": "6", "value": "{-1}"}, {"identifier": "7", "value": "set()"}, {"identifier": "8", "value": "set()"}], "fitness": "1.0", "parents": ["ec1e182c-2425-42f6-a1a9-4d49fe593145", "a7b0b63d-ccf5-4ff4-99b8-50e58add1fa0"]}, {"uuid": "11238998-d668-4983-9aa1-4769dfe6630c", "generation": 67, "genes": [{"identifier": "0", "value": "set()"}, {"identifier": "1", "value": "{-1}"}, {"identifier": "2", "value": "set()"}, {"identifier": "3", "value": "set()"}, {"identifier": "4", "value": "{2}"}, {"identifier": "5", "value": "set()"}, {"identifier": "6", "value": "{-1}"}, {"identifier": "7", "value": "set()"}, {"identifier": "8", "value": "set()"}], "fitness": "1.0", "parents": ["816ddab1-c722-438a-9301-573aa92c1506", "251d3579-6c7d-4502-90f2-4c0179207d7d"]}, {"uuid": "e9185bf0-80e6-472c-98c9-fb76cdd00b7a", "generation": 65, "genes": [{"identifier": "0", "value": "set()"}, {"identifier": "1", "value": "{-1}"}, {"identifier": "2", "value": "set()"}, {"identifier": "3", "value": "set()"}, {"identifier": "4", "value": "{2}"}, {"identifier": "5", "value": "{-1}"}, {"identifier": "6", "value": "{-1}"}, {"identifier": "7", "value": "set()"}, {"identifier": "8", "value": "set()"}], "fitness": "1.0", "parents": ["9fad086c-af71-4414-8dcc-0302645e2b32", "80008bb5-9ac7-4ce9-ab0d-63258eba7e02"]}], "best": 1.0, "average": 0.9523809523809523, "median": 0.0, "std": 0.21295885499998002}, {"generation": 67, "goal": "2", "chromosomes": [{"uuid": "a0d54f47-86c5-4fa7-8a4f-96dc326e6141", "generation": 15, "genes": [{"identifier": "0", "value": "set()"}, {"identifier": "1", "value": "set()"}, {"identifier": "2", "value": "{-1}"}, {"identifier": "3", "value": "{-1}"}, {"identifier": "4", "value": "{1}"}, {"identifier": "5", "value": "{-1}"}, {"identifier": "6", "value": "{-1}"}, {"identifier": "7", "value": "{-1}"}, {"identifier": "8", "value": "{-1}"}], "fitness": "1.0", "parents": ["788cf449-c1f8-4328-901b-fcd940fad99c", "875a0fb6-3bd3-4de6-80cf-4b14f8558bc1"]}, {"uuid": "45663355-7858-4810-81b1-d803a5e74472", "generation": 64, "genes": [{"identifier": "0", "value": "set()"}, {"identifier": "1", "value": "set()"}, {"identifier": "2", "value": "{-1}"}, {"identifier": "3", "value": "{-1}"}, {"identifier": "4", "value": "{1}"}, {"identifier": "5", "value": "{-1}"}, {"identifier": "6", "value": "set()"}, {"identifier": "7", "value": "{-1}"}, {"identifier": "8", "value": "set()"}], "fitness": "1.0", "parents": ["ef1e55b4-9c84-4cf3-bdbb-57bff6ec5293", "03427565-1f06-4921-bd12-72b373df83d2"]}, {"uuid": "98281b73-ca2b-41ac-b562-49f801fe842a", "generation": 66, "genes": [{"identifier": "0", "value": "set()"}, {"identifier": "1", "value": "set()"}, {"identifier": "2", "value": "{-1}"}, {"identifier": "3", "value": "{-1}"}, {"identifier": "4", "value": "{1}"}, {"identifier": "5", "value": "{-1}"}, {"identifier": "6", "value": "set()"}, {"identifier": "7", "value": "{-1}"}, {"identifier": "8", "value": "set()"}], "fitness": "1.0", "parents": ["a34d16f8-7337-46ea-bbf1-844877d27fdf", "2ffd1e4e-e162-40c0-a45e-d3d1c2968b89"]}, {"uuid": "47532091-76cf-4eb2-8140-ebbfbe92a02a", "generation": 67, "genes": [{"identifier": "0", "value": "set()"}, {"identifier": "1", "value": "set()"}, {"identifier": "2", "value": "{-1}"}, {"identifier": "3", "value": "set()"}, {"identifier": "4", "value": "{1}"}, {"identifier": "5", "value": "{-1}"}, {"identifier": "6", "value": "set()"}, {"identifier": "7", "value": "{-1}"}, {"identifier": "8", "value": "set()"}], "fitness": "1.0", "parents": ["ca3028d0-32a0-4fb7-99bc-59e382a23404", "3f112579-9958-4cc1-95e7-0dc70e005283"]}, {"uuid": "4266f00d-ce2c-49b2-b2c7-3b918a43cee4", "generation": 64, "genes": [{"identifier": "0", "value": "set()"}, {"identifier": "1", "value": "set()"}, {"identifier": "2", "value": "{-1}"}, {"identifier": "3", "value": "{-1}"}, {"identifier": "4", "value": "{1}"}, {"identifier": "5", "value": "{-1}"}, {"identifier": "6", "value": "set()"}, {"identifier": "7", "value": "{-1}"}, {"identifier": "8", "value": "set()"}], "fitness": "1.0", "parents": ["7480a35a-00e7-48bc-b682-5ab35c55c740", "ef1e55b4-9c84-4cf3-bdbb-57bff6ec5293"]}, {"uuid": "a34d16f8-7337-46ea-bbf1-844877d27fdf", "generation": 65, "genes": [{"identifier": "0", "value": "set()"}, {"identifier": "1", "value": "set()"}, {"identifier": "2", "value": "set()"}, {"identifier": "3", "value": "{-1}"}, {"identifier": "4", "value": "{1}"}, {"identifier": "5", "value": "{-1}"}, {"identifier": "6", "value": "set()"}, {"identifier": "7", "value": "{-1}"}, {"identifier": "8", "value": "set()"}], "fitness": "1.0", "parents": ["92e34e0a-2ed0-4adc-9d8b-3a97467d2807", "f4351c90-529c-4f17-8a76-fa6e4dd492c7"]}, {"uuid": "afe2c9c8-1732-4e15-bd66-f217cb225178", "generation": 67, "genes": [{"identifier": "0", "value": "set()"}, {"identifier": "1", "value": "set()"}, {"identifier": "2", "value": "{-1}"}, {"identifier": "3", "value": "{-1}"}, {"identifier": "4", "value": "{1}"}, {"identifier": "5", "value": "{-1}"}, {"identifier": "6", "value": "{-1}"}, {"identifier": "7", "value": "set()"}, {"identifier": "8", "value": "set()"}], "fitness": "1.0", "parents": ["a0d54f47-86c5-4fa7-8a4f-96dc326e6141", "98281b73-ca2b-41ac-b562-49f801fe842a"]}, {"uuid": "d171c5aa-d443-42f7-8f84-e937a7494c49", "generation": 66, "genes": [{"identifier": "0", "value": "set()"}, {"identifier": "1", "value": "set()"}, {"identifier": "2", "value": "{-1}"}, {"identifier": "3", "value": "{-1}"}, {"identifier": "4", "value": "{1}"}, {"identifier": "5", "value": "{-1}"}, {"identifier": "6", "value": "{-1}"}, {"identifier": "7", "value": "{-1}"}, {"identifier": "8", "value": "set()"}], "fitness": "1.0", "parents": ["03427565-1f06-4921-bd12-72b373df83d2", "a0d54f47-86c5-4fa7-8a4f-96dc326e6141"]}, {"uuid": "3f112579-9958-4cc1-95e7-0dc70e005283", "generation": 64, "genes": [{"identifier": "0", "value": "set()"}, {"identifier": "1", "value": "set()"}, {"identifier": "2", "value": "set()"}, {"identifier": "3", "value": "set()"}, {"identifier": "4", "value": "{1}"}, {"identifier": "5", "value": "{-1}"}, {"identifier": "6", "value": "set()"}, {"identifier": "7", "value": "{-1}"}, {"identifier": "8", "value": "set()"}], "fitness": "1.0", "parents": ["a8b22c0f-84bd-4249-9296-90d1b8b8d802", "03427565-1f06-4921-bd12-72b373df83d2"]}, {"uuid": "ca3028d0-32a0-4fb7-99bc-59e382a23404", "generation": 64, "genes": [{"identifier": "0", "value": "set()"}, {"identifier": "1", "value": "set()"}, {"identifier": "2", "value": "{-1}"}, {"identifier": "3", "value": "{-1}"}, {"identifier": "4", "value": "{1}"}, {"identifier": "5", "value": "{-1}"}, {"identifier": "6", "value": "set()"}, {"identifier": "7", "value": "{-1}"}, {"identifier": "8", "value": "set()"}], "fitness": "1.0", "parents": ["ba5d814a-cf8b-4603-b026-0732b9f3ebdf", "7f5a3147-e3d3-40b3-ae19-0733fc17a161"]}, {"uuid": "3312b65e-709e-4c59-af74-a95fab726cb6", "generation": 67, "genes": [{"identifier": "0", "value": "set()"}, {"identifier": "1", "value": "set()"}, {"identifier": "2", "value": "{-1}"}, {"identifier": "3", "value": "{-1}"}, {"identifier": "4", "value": "{1}"}, {"identifier": "5", "value": "{-1}"}, {"identifier": "6", "value": "set()"}, {"identifier": "7", "value": "{-1}"}, {"identifier": "8", "value": "set()"}], "fitness": "1.0", "parents": ["a0d54f47-86c5-4fa7-8a4f-96dc326e6141", "98281b73-ca2b-41ac-b562-49f801fe842a"]}, {"uuid": "7f5a3147-e3d3-40b3-ae19-0733fc17a161", "generation": 60, "genes": [{"identifier": "0", "value": "set()"}, {"identifier": "1", "value": "set()"}, {"identifier": "2", "value": "{-1}"}, {"identifier": "3", "value": "set()"}, {"identifier": "4", "value": "{1}"}, {"identifier": "5", "value": "{-1}"}, {"identifier": "6", "value": "set()"}, {"identifier": "7", "value": "{-1}"}, {"identifier": "8", "value": "set()"}], "fitness": "1.0", "parents": ["54b47667-0b3c-4857-bcbf-9d934342b592", "1c581302-8963-4718-bd69-fd51fde238ad"]}, {"uuid": "a8b22c0f-84bd-4249-9296-90d1b8b8d802", "generation": 63, "genes": [{"identifier": "0", "value": "set()"}, {"identifier": "1", "value": "set()"}, {"identifier": "2", "value": "set()"}, {"identifier": "3", "value": "set()"}, {"identifier": "4", "value": "{1}"}, {"identifier": "5", "value": "{-1}"}, {"identifier": "6", "value": "set()"}, {"identifier": "7", "value": "{-1}"}, {"identifier": "8", "value": "set()"}], "fitness": "1.0", "parents": ["92e34e0a-2ed0-4adc-9d8b-3a97467d2807", "7f5a3147-e3d3-40b3-ae19-0733fc17a161"]}, {"uuid": "80e53df4-9e85-4ed4-9de8-5eb4597ef094", "generation": 65, "genes": [{"identifier": "0", "value": "set()"}, {"identifier": "1", "value": "set()"}, {"identifier": "2", "value": "{-1}"}, {"identifier": "3", "value": "set()"}, {"identifier": "4", "value": "{1}"}, {"identifier": "5", "value": "{-1}"}, {"identifier": "6", "value": "{-1}"}, {"identifier": "7", "value": "{-1}"}, {"identifier": "8", "value": "set()"}], "fitness": "1.0", "parents": ["ac1993f2-1719-4590-8390-5fe1ccbb647c", "a0d54f47-86c5-4fa7-8a4f-96dc326e6141"]}, {"uuid": "be2640cb-6a3a-4a39-8a76-1d2c2e421173", "generation": 67, "genes": [{"identifier": "0", "value": "set()"}, {"identifier": "1", "value": "set()"}, {"identifier": "2", "value": "set()"}, {"identifier": "3", "value": "{-1}"}, {"identifier": "4", "value": "{1}"}, {"identifier": "5", "value": "set()"}, {"identifier": "6", "value": "set()"}, {"identifier": "7", "value": "{-1}"}, {"identifier": "8", "value": "set()"}], "fitness": "1.0", "parents": ["3f112579-9958-4cc1-95e7-0dc70e005283", "be9b6fa4-588f-4c95-8db8-a7572f3d116f"]}, {"uuid": "8c70b837-75aa-4e1a-8ba5-f47af2c8c7d3", "generation": 67, "genes": [{"identifier": "0", "value": "set()"}, {"identifier": "1", "value": "set()"}, {"identifier": "2", "value": "set()"}, {"identifier": "3", "value": "set()"}, {"identifier": "4", "value": "{1}"}, {"identifier": "5", "value": "{-1}"}, {"identifier": "6", "value": "set()"}, {"identifier": "7", "value": "{-1}"}, {"identifier": "8", "value": "set()"}], "fitness": "1.0", "parents": ["ca3028d0-32a0-4fb7-99bc-59e382a23404", "3f112579-9958-4cc1-95e7-0dc70e005283"]}, {"uuid": "b8f218df-6635-4013-beb6-f82af31238cf", "generation": 66, "genes": [{"identifier": "0", "value": "set()"}, {"identifier": "1", "value": "set()"}, {"identifier": "2", "value": "{-1}"}, {"identifier": "3", "value": "{-1}"}, {"identifier": "4", "value": "{1}"}, {"identifier": "5", "value": "{-1}"}, {"identifier": "6", "value": "set()"}, {"identifier": "7", "value": "{-1}"}, {"identifier": "8", "value": "set()"}], "fitness": "1.0", "parents": ["ba5d814a-cf8b-4603-b026-0732b9f3ebdf", "b33729d2-f910-43b9-865a-7d00f8fe0c10"]}, {"uuid": "25da83b8-c026-4bf0-aed2-adc92f2f64e2", "generation": 67, "genes": [{"identifier": "0", "value": "set()"}, {"identifier": "1", "value": "set()"}, {"identifier": "2", "value": "set()"}, {"identifier": "3", "value": "set()"}, {"identifier": "4", "value": "{1}"}, {"identifier": "5", "value": "{-1}"}, {"identifier": "6", "value": "set()"}, {"identifier": "7", "value": "{-1}"}, {"identifier": "8", "value": "set()"}], "fitness": "1.0", "parents": ["3f112579-9958-4cc1-95e7-0dc70e005283", "be9b6fa4-588f-4c95-8db8-a7572f3d116f"]}, {"uuid": "033bb831-d268-4b16-9a67-26436ced8234", "generation": 65, "genes": [{"identifier": "0", "value": "set()"}, {"identifier": "1", "value": "set()"}, {"identifier": "2", "value": "{-1}"}, {"identifier": "3", "value": "{-1}"}, {"identifier": "4", "value": "{1}"}, {"identifier": "5", "value": "{-1}"}, {"identifier": "6", "value": "set()"}, {"identifier": "7", "value": "{-1}"}, {"identifier": "8", "value": "set()"}], "fitness": "1.0", "parents": ["03427565-1f06-4921-bd12-72b373df83d2", "742eed8b-a9be-4638-90b5-878be150d85d"]}, {"uuid": "2ffd1e4e-e162-40c0-a45e-d3d1c2968b89", "generation": 65, "genes": [{"identifier": "0", "value": "set()"}, {"identifier": "1", "value": "set()"}, {"identifier": "2", "value": "{-1}"}, {"identifier": "3", "value": "set()"}, {"identifier": "4", "value": "{1}"}, {"identifier": "5", "value": "{-1}"}, {"identifier": "6", "value": "set()"}, {"identifier": "7", "value": "{-1}"}, {"identifier": "8", "value": "set()"}], "fitness": "1.0", "parents": ["92e34e0a-2ed0-4adc-9d8b-3a97467d2807", "f4351c90-529c-4f17-8a76-fa6e4dd492c7"]}, {"uuid": "0e4b12ca-378c-48ba-8298-862c2c2b9962", "generation": 66, "genes": [{"identifier": "0", "value": "set()"}, {"identifier": "1", "value": "set()"}, {"identifier": "2", "value": "{-1}"}, {"identifier": "3", "value": "{-1}"}, {"identifier": "4", "value": "{1}"}, {"identifier": "5", "value": "{-1}"}, {"identifier": "6", "value": "set()"}, {"identifier": "7", "value": "{-1}"}, {"identifier": "8", "value": "set()"}], "fitness": "1.0", "parents": ["ca3028d0-32a0-4fb7-99bc-59e382a23404", "b85ad027-b8a8-45e1-b958-c77162ea9023"]}], "best": 1.0, "average": 1.0, "median": 1.0, "std": 0.0}]}